Workbook

Sheet New Alumni DB
A1: ID | B1: Associate Number | C1: Full Name | D1: Surname | E1: First Name | F1: Middle Name | G1: Age Group | H1: Phone number | I1: Email | J1: Second Email | K1: LinkedIn | L1: Current Firm | M1: Current Role | N1: Current Role Seniority | O1: Current City | P1: Current Country | Q1: Curent Industry | R1: Notable Past Firms | S1: Past Role NPF | T1: Starting month NPF | U1: Ending Month NPF | V1: PR City | W1: PR City 2 | X1: PR City 3 | Y1: PR Country | Z1: PR Country 2 | AA1: PR Country 3 | AB1: NPF Industry | AC1: JEME Starting Period | AD1: JEME Ending Period | AE1: JEME Role | AF1: JEME Role 2 | AG1: JEME Role 3 | AH1: Board | AI1: Head
A2: 324 | B2: 329 | C2: Agnieszka Kania | D2: Kania | E2: Agnieszka | G2: 35-40 | I2: lesniewska.agnieszka@gmail.com | K2: https://www.linkedin.com/ignieszkadariakania/ | L2: Gsk | M2: Senior Manager Regulatory Platform Innovation | N2: C Level | O2: Milan | P2: IT | Q2: Healthcare & Pharma | R2: dotOne | S2: Business Analyst | T2: 01/2012 | U2: 01/2013 | V2: Kraków | Y2: PL | AB2: Technology & Software | AC2: 39387 | AD2: 40179 | AE2: Head of HR | AF2: Administrator | AH2: TRUE | AI2: TRUE
A3: 581 | B3: 70 | C3: Aiste Bielinyte | D3: Bielinyte | E3: Aiste | G3: 20-25 | I3: aiste.bielinyte@pimco.com | K3: https://www.linkedin.com/in/aistebielinyte/ | L3: PIMCO | M3: Account Analyst | N3: Entry level | O3: London | P3: GB | Q3: Financial Services | R3: Coinvest Capital | S3: Summer Intern | T3: 01/2022 | U3: 01/2022 | V3: Vilnius | Y3: LT | AB3: Financial Services | AC3: 44563 | AD3: 44929 | AE3: Associate Consultant | AH3: FALSE | AI3: FALSE
A4: 270 | B4: 2 | C4: Alberto Accogli | D4: Accogli | E4: Alberto | G4: 35-40 | I4: alberto.accogli@gmail.com | K4: https://www.linkedin.com/ilberto-accogli/ | L4: Boston Consulting Group (BCG) | M4: Principal | N4: Middle Level | O4: Dubai | P4: AE | Q4: Consulting & Advisory | R4: Leoni Corporate Advisors | S4: Manager | T4: 01/2012 | U4: 01/2019 | V4: Milan | Y4: IT | AB4: Consulting & Advisory | AC4: 38732 | AD4: 39447 | AE4: Secretary General | AF4: Head of HR | AH4: TRUE | AI4: TRUE
A5: 488 | B5: 20 | C5: Alberto Antoniolli | D5: Antoniolli | E5: Alberto | G5: 25-30 | I5: alberto.antoniolli@gmail.com | K5: https://www.linkedin.com/ilbertoantoniolli/ | L5: Lazard | M5: M&A Analyst | N5: Entry Level | O5: Milan | P5: IT | Q5: Consulting & Advisory | R5: Italmobiliare S.p.A. | S5: Intern Financial Analyst | T5: 06/2021 | U5: 09/2019 | V5: Milan | Y5: IT | AB5: Financial Services | AC5: 43626 | AD5: 44743 | AE5: Treasurer | AH5: TRUE | AI5: FALSE
A6: 526 | B6: 123 | C6: Alberto Cattaruzza | D6: Cattaruzza | E6: Alberto | G6: 25-30 | I6: cattaruzza98@gmail.com | K6: https://www.linkedin.com/in/alberto-cattaruzza-804a1a196/ | L6: Blackstone | M6: Associate | N6: Entry Level | O6: Milan | P6: IT | Q6: Financial Services | R6: Bank of America | S6: Investment Banking Analyst | T6: 07/2022 | U6: 12/2024 | V6: Milan | Y6: IT | AB6: Financial Services | AC6: 43891 | AD6: 44470 | AE6: Associate Consultant | AH6: FALSE | AI6: FALSE
B7: 138 | C7: Alberto Cifrodelli | D7: Cifrodelli | E7: Alberto | G7: 20-25 | I7: alberto.cifrodelli@studbocconi.it | K7: https://www.linkedin.com/in/albertocifrodelli | L7: BNP Paribas CIB | M7: Docente Master, Componente del Comitato Scientifico del Laboratorio di Finanza Decentralizzata e Blockchain (LabDEC) | N7: Entry level | O7: Milan | Q7: Financial Services | R7: Resolute Asset Management | S7: Co-Founder | T7: 01/2023 | U7: 01/2023 | V7: Milan | Y7: IT | AB7: Financial Services | AE7: Associate Consultant | AH7: FALSE | AI7: FALSE
A8: 202 | B8: 250 | C8: Alberto Franco | D8: Franco | E8: Alberto | I8: alberto.franco@cbalex.com | K8: https://www.linkedin.com/ilbertofrancoit | L8: Saa - School Ofnmanagement, Università Di Torino | M8: M&A Analyst | N8: Middle level | O8: Turin | P8: IT | Q8: Legal & Compliance | R8: CryptoLeges | S8: Financial Analyst | T8: 01/2015 | U8: Present | V8: Turin | Y8: IT | AB8: Education & Research | AE8: Associate Consultant | AH8: FALSE | AI8: FALSE
A9: 511 | B9: 320 | C9: Alberto Holler | D9: Holler | E9: Alberto | G9: 25-30 | I9: alberto.holler@gmail.com | K9: https://www.linkedin.com/ilberto-holler-72a95199/ | L9: Generali | M9: Investment Banking Off-Cycle Analyst | N9: Entry level | O9: Milan | P9: IT | Q9: Financial Services | R9: Deloitte | S9: Investment Analyst Intern | T9: 06/2021 | U9: 09/2021 | V9: Milan | Y9: IT | AB9: Consulting & Advisory | AC9: 43843 | AD9: 44627 | AE9: Secretary General | AH9: TRUE | AI9: FALSE
A10: 106 | B10: 386 | C10: Alberto Matuozzo | D10: Matuozzo | E10: Alberto | G10: 45-50 | I10: a.matuozzo@virtuosoadvisory.com | J10: alberto_matuozzo@yahoo.co.uk | K10: https://www.linkedin.com/in/alberto-matuozzo-2a504a8/ | L10: Virtuoso Advisory | M10: Director | N10: C Level | O10: London | P10: GB | Q10: Financial Services | R10: Farema Capital | S10: Partner | T10: 01/2012 | U10: 04/2016 | V10: London | Y10: GB | AB10: Financial Services | AC10: 35104 | AD10: 35766 | AE10: President | AH10: TRUE | AI10: FALSE
B11: 587 | C11: Alberto Vedovi | D11: Vedovi | E11: Alberto | G11: 30-35 | I11: albertovedovi@gmail.com | K11: https://www.linkedin.com/in/alberto-vedovi-cfa-caia-48832772/ | L11: NS Partners | M11: Principal Director | N11: Middle Level | O11: Luxembourg | Q11: Financial Services | R11: Deloitte | S11: Sustainability and Innovation Officer | T11: 01/2018 | U11: 09/2020 | V11: Luxembourg | Y11: LU | AB11: Consulting & Advisory | AC11: 42095 | AD11: 43040 | AE11: Vice President | AF11: Treasurer | AH11: TRUE | AI11: FALSE
A12: 174 | B12: 479 | C12: Aldo Pozzoli | D12: Pozzoli | E12: Aldo | G12: 40-45 | I12: aldopozzoli@hotmail.com | K12: https://www.linkedin.com/in/aldopozzoli/ | L12: Accenture | M12: Client Business Partner | N12: C Level | O12: Milan | P12: IT | Q12: Consulting & Advisory | R12: Comune di Milano | S12: International Business Senior Consultant | T12: 01/2007 | U12: 01/2011 | V12: Milan | Y12: IT | AB12: Public Sector & Non-Profit | AC12: 36871 | AD12: 37649 | AE12: Associate Consultant | AH12: FALSE | AI12: FALSE
A13: 217 | B13: 29 | C13: Alessandra Arrigoni | D13: Arrigoni | E13: Alessandra | G13: 40-45 | I13: alessandraarrigoni@hotmail.com | K13: https://www.linkedin.com/in/alessandra-arrigoni-8aa45b7/ | L13: NielsenIQ | M13: Financial Stability Intern | N13: C Level | O13: London | P13: GB | Q13: Technology & Software | R13: Nielsen | S13: Strategy Analyst Intern | T13: 01/2014 | U13: 01/2015 | V13: London | Y13: GB | AB13: Technology & Software | AC13: 37642 | AD13: 38007 | AE13: Associate Consultant | AH13: FALSE | AI13: FALSE
A14: 603 | B14: 238 | C14: Alessandra Fidone | D14: Fidone | E14: Alessandra | G14: 20-25 | I14: alessandrafidone@outlook.com | K14: https://www.linkedin.com/in/alessandrafidone/ | L14: Deutsche Bundesbank | N14: Entry level | O14: Frankfurt | P14: DE | Q14: Financial Services | R14: Knauf Insulation | T14: 01/2023 | U14: 01/2023 | V14: Brussels | Y14: BE | AB14: Industrial & Manufacturing | AC14: 44571 | AD14: 45666 | AE14: Head of Marketing | AH14: FALSE | AI14: TRUE
A15: 126 | B15: 268 | C15: Alessandra Galli | D15: Galli | E15: Alessandra | G15: 45-50 | I15: ale.galli76@gmail.com | M15: Corporate Tax Advisor | S15: Technical Advisor to the Judge | AC15: 35831 | AD15: 35990 | AE15: Associate Consultant | AH15: FALSE | AI15: FALSE
A16: 77 | B16: 357 | C16: Alessandra Mangeri | D16: Mangeri | E16: Alessandra | G16: 50-55 | I16: ale.mangeri@virgilio.it | K16: https://www.linkedin.com/in/alessandra-mangeri-6568903b/ | L16: Amg | M16: Distribution Manager | N16: Middle Level | O16: Cuneo | P16: IT | Q16: Financial Services | R16: Tribunale di Brescia | S16: Area Manager | T16: 01/2011 | U16: Present | V16: Brescia | Y16: IT | AB16: Public Sector & Non-Profit | AC16: 33865 | AD16: 37315 | AE16: Associate Consultant | AH16: FALSE | AI16: FALSE
A17: 307 | B17: 457 | C17: Alessandra Peres | D17: Peres | E17: Alessandra | G17: 35-40 | I17: alessandra_peres@swissre.com | K17: https://www.linkedin.com/ilessandra-peres-21b2a2b/ | L17: Swiss Re Corporate Solutions | M17: Vice President Customer Value Creation | N17: Middle Level | O17: Milan | P17: IT | Q17: Financial Services | R17: FC Rimaco - Stellantis | S17: Product innovation and business director | T17: 01/2020 | U17: 01/2023 | V17: Lugano | Y17: CH | AB17: Financial Services | AC17: 39329 | AD17: 40513 | AE17: Vice President | AH17: FALSE | AI17: FALSE
A18: 131 | B18: 599 | C18: Alessandra Vultaggio | D18: Vultaggio | E18: Alessandra | G18: 45-50 | I18: alexvulty@gmail.com | K18: https://www.linkedin.com/in/alessandravultaggio/ | L18: Global Blue | M18: Senior Advisor | N18: C Level | O18: Milan | P18: IT | Q18: Financial Services | R18: Edenred Italia | S18: Group Chief Information Officer | T18: 05/2011 | U18: 11/2019 | V18: Milan | Y18: IT | AB18: Financial Services | AC18: 35831 | AD18: 37298 | AE18: President | AH18: TRUE | AI18: FALSE
A19: 6 | B19: 9 | C19: Alessandro Alloisio | D19: Alloisio | E19: Alessandro | G19: 55-60 | I19: alessandroalloisio@gmail.com | K19: https://www.linkedin.com/ilessandro-alloisio-9a13a/ | L19: Freelancer (Self-Employed) | O19: Como | P19: IT | R19: Sanlorenzo | T19: 01/2021 | U19: 10/2025 | V19: Ameglia | Y19: IT | AB19: Consumer & Retail | AC19: 32464 | AD19: 34233 | AE19: Administrator | AH19: TRUE | AI19: FALSE
A20: 1 | B20: 52 | C20: Alessandro Bellotti | D20: Bellotti | E20: Alessandro | M20: Responsabile Specialisti Investimenti | S20: District manager | AH20: FALSE | AI20: FALSE
A21: 72 | B21: 84 | C21: Alessandro Brambilla | D21: Brambilla | E21: Alessandro | G21: 50-55 | K21: https://www.linkedin.com/in/alessandro-brambilla-24522121/ | L21: Mediobanca Premier | M21: Investment Professional | N21: Middle Level | O21: Milan | P21: IT | Q21: Financial Services | R21: Barclays | S21: Associate | T21: 01/2013 | U21: 08/2016 | V21: Milan | Y21: IT | AB21: Financial Services | AC21: 33419 | AD21: 34466 | AE21: President | AH21: TRUE | AI21: FALSE
A22: 411 | B22: 90 | C22: Alessandro Brutto | D22: Brutto | E22: Alessandro | G22: 25-30 | I22: bruttoalessandro@gmail.com | K22: https://www.linkedin.com/ilessandro-brutto-bb15117 | L22: Cinven | M22: Staff Product Manager | N22: Middle Level | O22: London | P22: GB | Q22: Financial Services | R22: Goldman Sachs | S22: Head of Product | T22: 11/2021 | U22: 06/2024 | V22: London | Y22: GB | AB22: Financial Services | AC22: 42513 | AD22: 42790 | AE22: Associate Consultant | AH22: FALSE | AI22: FALSE
A23: 426 | B23: 174 | C23: Alessandro Dadone | D23: Dadone | E23: Alessandro | G23: 25-30 | I23: aledadone@gmail.com | K23: https://www.linkedin.com/ilessandro-dadone-23196318 | L23: Qonto | M23: Associate | N23: Middle Level | O23: Paris | P23: FR | Q23: Financial Services | R23: Casavo | S23: Consultant | T23: 05/2022 | U23: 03/2024 | V23: Milan | Y23: IT | AB23: Technology & Software | AC23: 42751 | AD23: 43472 | AE23: Associate Consultant | AH23: FALSE | AI23: FALSE
A24: 429 | B24: 242 | C24: Alessandro Filoramo | D24: Filoramo | E24: Alessandro | I24: alessandro.filoram@gmail.com | K24: https://www.linkedin.com/ilessandrofiloramo | L24: Oliver Wyman | M24: Vice-President | N24: Entry level | O24: Dubai | P24: AE | Q24: Consulting & Advisory | R24: Arthur D. Little | S24: Vice President | T24: 09/2021 | U24: 03/2024 | V24: Dubai | Y24: AE | AB24: Consulting & Advisory | AE24: President | AH24: FALSE | AI24: FALSE
A25: 192 | B25: 261 | C25: Alessandro Gagliardi | D25: Gagliardi | E25: Alessandro | G25: 45-50 | I25: alessandro.gagliardi@hsbc.com | K25: https://www.linkedin.com/ilessandro-gagliardi/ | L25: Hsbc | M25: GTM Manager | N25: C Level | O25: London | P25: GB | Q25: Financial Services | R25: GE Capital | S25: M&A Intern | T25: 09/2008 | U25: 07/2016 | V25: London | Y25: GB | AB25: Financial Services | AC25: 37013 | AD25: 37298 | AE25: Associate Consultant | AH25: FALSE | AI25: FALSE
A26: 514 | B26: 393 | C26: Alessandro Medico | D26: Medico | E26: Alessandro | G26: 25-30 | H26: +393331968961 | I26: alemedi@icloud.com | K26: https://www.linkedin.com/ilessandro-medico/ | L26: Revel8 | M26: Investment Banking Analyst | N26: Middle Level | O26: Berlin | P26: DE | Q26: Technology & Software | R26: Bending Spoons | S26: Investment Banking Analyst | T26: 01/2021 | U26: 04/2022 | V26: Milan | Y26: IT | AB26: Technology & Software | AE26: Associate Consultant | AH26: FALSE | AI26: FALSE
A27: 561 | B27: 441 | C27: Alessandro Paladino | D27: Paladino | E27: Alessandro | G27: 25-30 | I27: alessandro.paladino.ts@gmail.com | K27: https://www.linkedin.com/in/alessandropaladino/ | L27: Morgan Stanley | M27: President | N27: Entry level | O27: Dubai | P27: AE | Q27: Financial Services | R27: Rothschild & Co | S27: Engagement Manager | T27: 01/2024 | U27: 01/2024 | V27: Dubai | Y27: AE | AB27: Financial Services | AE27: Secretary General | AH27: TRUE | AI27: TRUE
A28: 255 | B28: 487 | C28: Alessandro Radici | D28: Radici | E28: Alessandro | G28: 40-45 | I28: alessandro.radici@seragro.com.ar | K28: https://www.linkedin.com/ilessandro-radici-9988317/ | L28: Ser Beef | M28: Graduate Management Trainee | N28: C Level | O28: San Luis | Q28: Consulting & Advisory | R28: McKinsey & Company | S28: Corporate Finance Intern | T28: 08/2012 | U28: 07/2015 | V28: New Jersey | Y28: US | AB28: Consulting & Advisory | AC28: 38356 | AD28: 39083 | AE28: Vice President | AH28: TRUE | AI28: FALSE
A29: 610 | B29: 550 | C29: Alessandro Sozzani | D29: Sozzani | E29: Alessandro | G29: 25-30 | I29: alessandro.sozzani@hotmail.it | J29: alessandro.sozzani@ab-inbev.com | K29: https://www.linkedin.com/in/alessandro-sozzani/ | L29: AB InBev | M29: Fund Administration Analyst | N29: Entry level | P29: US | R29: Barilla Group | S29: Junior Aufitor | T29: 01/2024 | U29: 01/2024 | V29: Singapore | Y29: SG | AB29: Food & Beverage | AC29: 44571 | AD29: 45663 | AE29: Associate Consultant | AH29: FALSE | AI29: FALSE
A30: 553 | B30: 576 | C30: Alessandro Trisciuoglio | D30: Trisciuoglio | E30: Alessandro | G30: 25-30 | I30: aletrisc@gmail.com | K30: https://www.linkedin.com/ilessandro-trisciuoglio/ | L30: Heritage Holdings | M30: Senior Financial Analyst | N30: Entry Level | O30: Milan | P30: IT | Q30: Financial Services | R30: PwC | S30: Intern | T30: 01/2023 | U30: 01/2023 | V30: Milan | Y30: IT | AB30: Consulting & Advisory | AC30: 44075 | AD30: 44562 | AE30: Associate Consultant | AH30: FALSE | AI30: FALSE
A31: 472 | B31: 3 | C31: Alessia Acquistapace | D31: Acquistapace | E31: Alessia | G31: 25-30 | I31: alessia.a@amazon.com | K31: https://www.linkedin.com/in/alessiaacquistapace/ | L31: Amazon | M31: Praticante Notaio | N31: Middle Level | O31: London | P31: GB | Q31: Consumer & Retail | R31: Rothschild & Co | S31: Praticante Avvocato | T31: 06/2021 | U31: 01/2021 | V31: Milan | Y31: IT | AB31: Financial Services | AC31: 43255 | AD31: 44835 | AE31: Associate Consultant | AH31: FALSE | AI31: FALSE
A32: 469 | B32: 8 | C32: Alessia Alberti | D32: Alberti | E32: Alessia | G32: 25-30 | I32: alessia.alberti96@gmail.com | K32: https://www.linkedin.com/ilessia-alberti-b75a612b/ | L32: Roveda Laurini Clerici D’Amore Notai | M32: Dottore Commercialista - Revisore Legale | N32: Entry level | O32: Milan | P32: IT | Q32: Legal & Compliance | R32: BonelliErede | S32: Dottore Commercialista - Revisore Legale | T32: 02/2022 | U32: 07/2022 | V32: Milan | Y32: IT | AB32: Legal & Compliance | AC32: 43255 | AD32: 43871 | AE32: Associate Consultant | AH32: FALSE | AI32: FALSE
A33: 124 | B33: 197 | C33: Alessia Della Vedova | D33: Della Vedova | E33: Alessia | G33: 45-50 | K33: https://www.linkedin.com/ilessia-dellavedova/ | L33: Ls Lexjus Sinacta | M33: Managing Director Italy | N33: Entry level | Q33: Legal & Compliance | R33: Russo De Rosa Associati | S33: Go-to-Market Strategy Senior Manager | T33: 09/2019 | U33: 06/2024 | V33: Milan | Y33: IT | AB33: Legal & Compliance | AC33: 35831 | AD33: 36121 | AE33: Associate Consultant | AH33: FALSE | AI33: FALSE
A34: 361 | B34: 244 | C34: Alessia Fontanari | D34: Fontanari | E34: Alessia | G34: 30-35 | I34: alessiafon@gmail.com | J34: alessia@mapotapo.com | K34: https://www.linkedin.com/ilessiafontanari | L34: Flatpay | M34: CEO and owner | N34: C Level | O34: Milan | P34: IT | Q34: Financial Services | R34: Doctolib | S34: Consultant | T34: 01/2022 | U34: 12/2024 | V34: Milan | Y34: IT | AB34: Healthcare & Pharma | AC34: 41310 | AD34: 42499 | AE34: Head of Sales | AH34: FALSE | AI34: TRUE
A35: 112 | B35: 87 | C35: Alessio Bressan | D35: Bressan | E35: Alessio | G35: 45-50 | I35: alessio.bressan@igbressan.it | K35: https://www.linkedin.com/ilessio-bressan-8b26b/ | L35: IGB - Industrie Grafiche Bressan | M35: Owner | N35: C Level | O35: Milan | P35: IT | R35: EY | S35: Manager | T35: 01/1998 | U35: 01/1999 | AB35: Consulting & Advisory | AC35: 35488 | AD35: 35766 | AE35: Associate Consultant | AH35: FALSE | AI35: FALSE
B36: 237 | C36: Alessio Ficara | D36: Ficara | E36: Alessio | F36: Fortunato | G36: 45-50 | I36: alessioficara@gmail.com | K36: https://www.linkedin.com/in/alessiofortunatoficara/ | L36: La Maison | M36: Guide-conférencier | N36: C Level | O36: Milan | P36: IT | Q36: Other / Unclassified | R36: Jobseeker | S36: Language Teacher | T36: 01/2018 | U36: Present | V36: Milan | Y36: IT | AB36: Technology & Software | AC36: 35831 | AD36: 37298 | AE36: Treasurer | AH36: TRUE | AI36: FALSE
A37: 127 | B37: 348 | C37: Alessio Loreti | D37: Loreti | E37: Alessio | G37: 45-50 | K37: https://www.linkedin.com/in/alessio-loreti/ | L37: Freelance Self-Employed | M37: Executive Director | O37: Marseille | P37: FR | Q37: Education & Research | R37: Queen Mary University of London | S37: Managing Director | T37: 09/2004 | U37: 03/2005 | V37: London | Y37: GB | AB37: Education & Research | AC37: 35831 | AD37: 36121 | AE37: Associate Consultant | AH37: FALSE | AI37: FALSE
A38: 91 | B38: 124 | C38: Alex Cecchini | D38: Cecchini | E38: Alex | G38: 50-55 | I38: alex.cecchini@me.com | K38: https://www.linkedin.com/ilex-cecchini-579278/ | L38: Bank J. Safra Sarasin Ltd | M38: Member Board Of Directors | N38: C Level | O38: Lugano | P38: IE | Q38: Financial Services | R38: LGT Private Banking | S38: Member of Boad of Directors | T38: 06/2019 | U38: 01/2022 | V38: Lugano | Y38: CH | AB38: Financial Services | AC38: 34236 | AD38: 34347 | AE38: Associate Consultant | AH38: FALSE | AI38: FALSE
A39: 141 | B39: 223 | C39: Alex Fattorini | D39: Fattorini | E39: Alex | G39: 45-50 | K39: https://www.linkedin.com/ilex-fattorini-263999/ | L39: Mcarthurglen Group | M39: Head of Strategy & Operations | N39: C Level | Q39: Consumer & Retail | R39: Primonial REIM Italy | S39: Consultant - Digital | T39: 09/2022 | V39: Milan | Y39: IT | AB39: Consulting & Advisory | AC39: 36280 | AD39: 36584 | AE39: Associate Consultant | AH39: FALSE | AI39: FALSE
B40: 606 | C40: Alice Zarantonello | D40: Zarantonello | E40: Alice | G40: 25-30 | I40: alicezarantonello@outlook.com | K40: https://www.linkedin.com/in/alice-zarantonello000/ | L40: HIOP | M40: President | N40: Middle Level | O40: Milan | P40: IT | Q40: Technology & Software | R40: McKinsey & Company | S40: Administrative Consultant | T40: 01/2022 | U40: 01/2024 | V40: Milan | Y40: IT | AB40: Technology & Software | AC40: 43255 | AD40: 43774 | AE40: Associate Consultant | AH40: FALSE | AI40: FALSE
A41: 140 | B41: 72 | C41: Alvise Biffi | D41: Biffi | E41: Alvise | G41: 45-50 | I41: a.biffi@securenetwork.it | K41: https://www.linkedin.com/ilvise-biffi-115aa5/ | L41: Assolombarda | M41: Associate | N41: C Level | O41: Milan | P41: IT | Q41: Technology & Software | R41: Camera di Commercio Milano Monza Brianza Lodi | S41: Intern | T41: 05/2024 | U41: Present | V41: Milan | Y41: IT | AB41: Public Sector & Non-Profit | AC41: 36280 | AD41: 36861 | AE41: President | AH41: TRUE | AI41: FALSE
A42: 485 | B42: 317 | C42: Amin Harbi | D42: Harbi | E42: Amin | G42: 25-30 | I42: aharbi13@gmail.com | K42: https://www.linkedin.com/in/amin-harbi/ | L42: Boston Consulting Group (Bcg) | M42: CEO | N42: Entry Level | O42: Milan | P42: IT | Q42: Consulting & Advisory | R42: HSBC | S42: Board Member | T42: 05/2022 | U42: 10/2022 | V42: Milan | Y42: IT | AB42: Financial Services | AC42: 43480 | AD42: 44567 | AE42: Associate Consultant | AH42: FALSE | AI42: FALSE
B43: 274 | C43: Andre Gardella | D43: Gardella | E43: Andre | G43: 50-55 | I43: agardelik@gmail.com | K43: https://www.linkedin.com/in/andre-gardella-677304/ | L43: Treezor | M43: CEO | N43: C Level | O43: Paris | P43: FR | Q43: Financial Services | R43: PayXpert | S43: Head of Operations and Transformation | T43: 01/2025 | U43: Present | V43: London | Y43: GB | AB43: Financial Services | AC43: 33970 | AD43: 34700 | AE43: International Manager | AH43: FALSE | AI43: TRUE
A44: 87 | B44: 273 | C44: André Gardella | D44: Gardella | E44: André | G44: 50-55 | I44: agardelik@gmail.com | K44: https://www.linkedin.com/in/andre-gardella-677304/ | L44: Treezor | M44: Director of AI strategy & Engineering | N44: C Level | O44: Paris | P44: FR | R44: Société Générale | S44: Lead Data Scientist | T44: 07/2019 | U44: 01/2023 | V44: Paris | Y44: FR | AB44: Financial Services | AC44: 34236 | AD44: 34824 | AE44: International Manager | AH44: TRUE | AI44: FALSE
A45: 595 | B45: 37 | C45: Andrea Ballacchino | D45: Ballacchino | E45: Andrea | G45: 20-25 | I45: andreballacchino@gmail.com | K45: https://www.linkedin.com/in/andrea-ballacchino/ | L45: Simon-Kucher & Partners | M45: Associate Consultant | N45: Entry level | O45: London | P45: GB | Q45: Consulting & Advisory | R45: T8P Consulting | S45: Business Analyst | T45: 01/2024 | U45: 01/2024 | V45: Milan | Y45: IT | AB45: Consulting & Advisory | AC45: 44571 | AD45: 45665 | AE45: Treasurer | AH45: TRUE | AI45: TRUE
B46: 46 | C46: Andrea Baroni | D46: Baroni | E46: Andrea | F46: Augusto | G46: 30-35 | I46: andrea.augusto.baroni@gmail.com | K46: https://www.linkedin.com/iabaroni/ | L46: Barclays | M46: Global Category Director SDA and Watercare | N46: C Level | O46: London | P46: GB | Q46: Financial Services | R46: Travelport | S46: Strategic Planning Manager | T46: 01/2017 | U46: 01/2018 | V46: London | Y46: GB | AB46: Technology & Software | AC46: 41666 | AD46: 42268 | AE46: Treasurer | AH46: TRUE | AI46: FALSE
A47: 278 | B47: 58 | C47: Andrea Bergamini | D47: Bergamini | E47: Andrea | G47: 35-40 | I47: anbergamini@gmail.com | K47: https://www.linkedin.com/in/andrea-bergamini-40695b6/ | L47: Electrolux | M47: Category Leader Sports and Toys | N47: C Level | O47: Stockholm | Q47: Technology & Software | R47: Whirlpool | S47: Manager | T47: 04/2015 | U47: 12/2015 | V47: Comerio | Y47: IT | AB47: Technology & Software | AC47: 38860 | AD47: 39882 | AE47: Vice President | AH47: TRUE | AI47: FALSE
A48: 308 | B48: 63 | C48: Andrea Bertè | D48: Bertè | E48: Andrea | G48: 40-45 | I48: andrea.bertè@yahoo.it | J48: andreabertè@47northproductions.com | K48: https://www.linkedin.com/indrea-berte-38446947/ | L48: Amazon | M48: Associate | N48: C Level | O48: Dubai | P48: AE | Q48: Consumer & Retail | R48: zeb consulting | S48: Legal Intern | T48: 05/2017 | U48: 01/2018 | V48: Milan | Y48: IT | AB48: Consulting & Advisory | AC48: 39329 | AD48: 40190 | AE48: Associate Consultant | AH48: FALSE | AI48: FALSE
A49: 524 | B49: 112 | C49: Andrea Carvelli | D49: Carvelli | E49: Andrea | G49: 25-30 | I49: andrea.carvelli@lw.com | K49: https://www.linkedin.com/in/andrea-carvelli/ | L49: Latham & Watkins | M49: Strategic Projects | N49: Entry Level | O49: Milan | P49: IT | Q49: Legal & Compliance | R49: Baker McKenzie | S49: Team Leader | T49: 05/2021 | U49: 08/2021 | V49: Milan | Y49: IT | AB49: Consulting & Advisory | AC49: 43831 | AD49: 44927 | AE49: Associate Consultant | AH49: FALSE | AI49: FALSE
A50: 501 | B50: 203 | C50: Andrea Di Benedetto | D50: Di Benedetto | E50: Andrea | G50: 25-30 | I50: andrea.dibenedetto@ftidelta.com | K50: https://www.linkedin.com/in/andrea-di-benedetto-bbb463111/ | L50: City Football Group | M50: Transformation Lead | N50: Entry Level | O50: Riyadh | P50: SA | Q50: Other / Unclassified | R50: Delta Partners | S50: Engagement Manager | T50: 01/2023 | U50: 07/2025 | V50: Dubai | Y50: AE | AB50: Consulting & Advisory | AC50: 43506 | AD50: 43800 | AE50: Associate Consultant | AH50: FALSE | AI50: FALSE
A51: 334 | B51: 210 | C51: Andrea Di Pietrantonio | D51: Di Pietrantonio | E51: Andrea | G51: 30-35 | I51: andricon@hotmail.it | K51: https://www.linkedin.com/in/andreadipietrantonio/ | L51: Iceye | M51: Founder | N51: Middle level | O51: Helsinki | P51: FI | Q51: Public Sector & Non-Profit | R51: McKinsey & Company | S51: Founder | T51: 09/2022 | U51: 10/2025 | V51: Helsinki | Y51: FI | AB51: Consulting & Advisory | AC51: 40568 | AD51: 41296 | AE51: Vice President | AH51: TRUE | AI51: FALSE
A52: 222 | B52: 285 | C52: Andrea Gerosa | D52: Gerosa | E52: Andrea | G52: 40-45 | I52: andreagerosa@hotmail.com | K52: https://www.linkedin.com/in/andreagerosa/ | L52: Thinkyoung | M52: Managing Director Structured Credit Trading | N52: C Level | O52: Brussels | P52: BE | Q52: Education & Research | R52: Entrepreneurship Club | S52: Director | T52: 01/2011 | U52: Present | V52: New York | Y52: US | AB52: Public Sector & Non-Profit | AC52: 37642 | AD52: 39083 | AE52: President of JADE | AH52: FALSE | AI52: FALSE
A53: 299 | B53: 287 | C53: Andrea Gherzi | D53: Gherzi | E53: Andrea | G53: 35-40 | I53: a.gherzi@hotmail.it | K53: https://www.linkedin.com/in/andrea-gherzi-21a44016/ | L53: Nomura | M53: CEO | N53: C Level | Q53: Financial Services | R53: Credit Suisse | S53: Head of Strategy | T53: 01/2010 | U53: 01/2024 | V53: London | Y53: GB | AB53: Financial Services | AC53: xx/2007 | AD53: xx/2009 | AE53: Treasurer | AH53: TRUE | AI53: FALSE
A54: 188 | B54: 288 | C54: Andrea Ghizzoni | D54: Ghizzoni | E54: Andrea | G54: 40-45 | I54: andrea.ghizzoni79@gmail.com | J54: andrea.ghizzoni@facile.it | K54: https://www.linkedin.com/indreaghizzoni/ | L54: Facile.It | M54: Business Analyst | N54: C Level | O54: Milan | P54: IT | Q54: Technology & Software | R54: Vodafone | T54: 11/2019 | U54: 08/2021 | V54: Milan | Y54: IT | AB54: Technology & Software | AC54: 37013 | AD54: 37649 | AE54: Associate Consultant | AH54: FALSE | AI54: FALSE
A55: 512 | B55: 333 | C55: Andrea La Torre | D55: La Torre | E55: Andrea | I55: andrealatorre.alt@gmail.com | K55: https://www.linkedin.com/indrea-la-torre-34b67b7/ | L55: Iziwork | M55: Partner | N55: Entry level | O55: Milan | P55: IT | Q55: Human Capital & Services | S55: Analyst | AC55: 43843 | AE55: Associate Consultant | AH55: FALSE | AI55: FALSE
A56: 214 | B56: 341 | C56: Andrea Lazzari | D56: Lazzari | E56: Andrea | G56: 40-45 | I56: andrea.lazzari@gmail.com | K56: https://www.linkedin.com/indrea-lazzari-94158519 | L56: Venice Investment | M56: Associate | N56: C Level | O56: London | P56: GB | Q56: Financial Services | R56: Credit Suisse | S56: Private Equity Analyst Intern | T56: 08/2007 | U56: 01/2009 | V56: London | Y56: GB | AB56: Financial Services | AC56: 37387 | AD56: 38007 | AE56: Associate Consultant | AH56: FALSE | AI56: FALSE
A57: 465 | B57: 343 | C57: Andrea Lippa | D57: Lippa | E57: Andrea | G57: 25-30 | I57: alippa@bu.edu | J57: lippa.andrea@libero.it | K57: https://www.linkedin.com/indrea-lippa-26718311b/ | L57: Mckinsey & Company | M57: Experience Transformation Manager | N57: Middle Level | O57: Milan | P57: IT | Q57: Consulting & Advisory | R57: White Bridge Investments | S57: Intern | T57: 01/2021 | U57: 04/2021 | V57: Milan | Y57: IT | AB57: Financial Services | AC57: 43255 | AD57: 43905 | AE57: Associate Consultant | AH57: FALSE | AI57: FALSE
A58: 404 | B58: 353 | C58: Andrea Maggi | D58: Maggi | E58: Andrea | G58: 30-35 | I58: a_maggi@ymail.com | J58: andrea.maggi@accenture.com | K58: https://www.linkedin.com/in/maggiandrea | L58: Accenture | M58: Independent Financial Services Professional | N58: Middle Level | O58: Milan | P58: IT | Q58: Consulting & Advisory | R58: Emirates Investment Bank PJSC | T58: 07/2017 | U58: 01/2017 | V58: Dubai | Y58: AE | AB58: Financial Services | AC58: 42278 | AD58: 43040 | AE58: Vice President | AH58: TRUE | AI58: FALSE
A59: 65 | B59: 361 | C59: Andrea Maralla | D59: Maralla | E59: Andrea | G59: 50-55 | I59: andrea.maralla@fastwebnet.it | K59: https://www.linkedin.com/in/andrea-maralla-522b327/ | M59: Researcher | S59: Assistant Designer | AC59: 33419 | AD59: 34233 | AE59: Associate Consultant | AH59: FALSE | AI59: FALSE
A60: 265 | B60: 385 | C60: Andrea Matranga | D60: Matranga | E60: Andrea | G60: 40-45 | I60: andreamatranga@gmail.com | K60: https://www.linkedin.com/imatranga | L60: Università Degli Studi Di Torino | M60: Principal Program Manager | N60: Middle Level | O60: Turin | P60: IT | Q60: Education & Research | R60: Nordstrom | S60: Senior Consultant | T60: 08/2011 | U60: 02/2015 | V60: Seattle | Y60: US | AB60: Consumer & Retail | AC60: 38416 | AD60: 38860 | AE60: Associate Consultant | AH60: FALSE | AI60: FALSE
A61: 351 | B61: 440 | C61: Andrea Paladini | D61: Paladini | E61: Andrea | G61: 30-35 | I61: paladini.andre@gmail.com | K61: https://www.linkedin.com/indrea-paladini-6b884a77 | L61: Amazon | M61: Senior Advisor | N61: Middle Level | O61: Milan | P61: IT | Q61: Consumer & Retail | R61: Bain & Company | S61: Sourcing & Origination | T61: 01/2018 | U61: 01/2020 | V61: Milan | Y61: IT | AB61: Consulting & Advisory | AC61: 40567 | AD61: 41799 | AE61: Treasurer | AH61: TRUE | AI61: FALSE
A62: 98 | B62: 503 | C62: Andrea Ronchiato | D62: Ronchiato | E62: Andrea | G62: 50-55 | I62: andrearonchiato@hotmail.com | K62: https://www.linkedin.com/in/andrea-ronchiato-8216512/ | L62: Banca Investis | M62: Counsel | N62: Middle Level | O62: London | P62: GB | Q62: Financial Services | R62: SC Lowy | S62: Senior Associate | T62: 01/2021 | U62: 07/2024 | V62: London | Y62: GB | AB62: Financial Services | AC62: 34658 | AD62: 34974 | AE62: Administrator | AH62: TRUE | AI62: FALSE
A63: 296 | B63: 522 | C63: Andrea Salsi | D63: Salsi | E63: Andrea | G63: 35-40 | I63: andrea.salsi@hotmail.it | J63: andrea.salsi@nortonrose.com | K63: https://www.linkedin.com/indrea-salsi-6722339 | L63: Norton Rose Fulbright | M63: Founder | N63: Middle Level | O63: London | P63: GB | Q63: Legal & Compliance | R63: Hogan Lovells | S63: Lead Analytics Engineer | T63: 01/2016 | U63: 05/2024 | V63: London | Y63: GB | AB63: Legal & Compliance | AC63: 39098 | AD63: 39882 | AE63: Associate Consultant | AH63: FALSE | AI63: FALSE
A64: 408 | B64: 524 | C64: Andrea Salvati | D64: Salvati | E64: Andrea | G64: 25-30 | I64: andrea@hiluxia.com | K64: https://www.linkedin.com/indrea-salvati | L64: Luxia | M64: Senior Associate | N64: C Level | O64: Milan | P64: IT | R64: Cleo (and also DAZN) | S64: Investment Analyst | T64: 01/2023 | U64: 02/2024 | V64: London | Y64: GB | AB64: Financial Services | AC64: 42380 | AD64: 43251 | AE64: Head of IT | AF64: Head of Communications | AH64: FALSE | AI64: TRUE
A65: 392 | B65: 533 | C65: Andrea Schettini | D65: Schettini | E65: Andrea | G65: 30-35 | I65: andrea.schettini22@gmail.com | K65: https://www.linkedin.com/in/andreaschettini/ | L65: BlueGem Capital Partners | M65: Competition, Antitrust and Regulatory Litigation | N65: C Level | O65: London | P65: GB | Q65: Financial Services | R65: BlueGem Capital Partners | S65: Senior Legal Counsel | T65: 01/2020 | U65: 12/2022 | V65: London | Y65: GB | AB65: Financial Services | AC65: 42023 | AD65: 42982 | AE65: Head of Sales | AH65: FALSE | AI65: TRUE
A66: 258 | B66: 563 | C66: Andrea Tel | D66: Tel | E66: Andrea | G66: 35-40 | I66: andrea.tel@gmail.com | K66: https://www.linkedin.com/in/andreatel/ | L66: Amazon | M66: Data Science Consultant | N66: Middle Level | O66: Milan | P66: IT | Q66: Consumer & Retail | R66: BAT | S66: Data Science Intern | T66: 11/2017 | U66: 05/2021 | V66: London | Y66: GB | AB66: Industrial & Manufacturing | AC66: 38356 | AE66: President | AH66: TRUE | AI66: FALSE
A67: 593 | B67: 582 | C67: Andrea Valacchi | D67: Valacchi | E67: Andrea | G67: 20-25 | I67: andreavalacchi288@gmail.com | K67: https://www.linkedin.com/in/andrea-valacchi-1519ba225/ | L67: Fujitsu | N67: Entry level | O67: New York | P67: US | Q67: Consulting & Advisory | R67: Coca-Cola | T67: 01/2025 | U67: 01/2025 | V67: Dallas | Y67: US | AB67: Food & Beverage | AE67: Associate Consultant | AH67: FALSE | AI67: FALSE
A68: 201 | B68: 328 | C68: Aneta Kacprzak | D68: Kacprzak | E68: Aneta | G68: 40-45 | M68: Sales Area Manager | S68: Business Development Manager | AC68: 37278 | AD68: 38007 | AE68: Administrator | AH68: TRUE | AI68: FALSE
B69: 240 | C69: Angela Filippa | D69: Filippa | E69: Angela | G69: 50-55 | I69: angela.filippa@csfb.com | K69: https://www.linkedin.com/in/angela-filippa/ | L69: Barclays | M69: Associate Professor in Strategy | N69: Middle Level | O69: New York | P69: US | Q69: Financial Services | R69: Credit Suisse | T69: 06/1998 | U69: 07/2021 | V69: New York | W69: London | Y69: US | Z69: GB | AB69: Financial Services | AC69: 33769 | AE69: Associate Consultant | AH69: FALSE | AI69: FALSE
A70: 67 | B70: 454 | C70: Angelo Peluffo | D70: Peluffo | E70: Angelo | G70: 50-55 | I70: peluffan@gmail.com | J70: angelo.peluffo@fiat.com | K70: https://www.linkedin.com/in/angelopeluffo/ | L70: Fiat Chrysler Automobiles (FCA) | N70: Middle Level | O70: Bologna | P70: IT | Q70: Industrial & Manufacturing | R70: BASF Coatings Refinish S.p.A. | T70: 03/2001 | U70: 10/2001 | V70: Milan | Y70: IT | AB70: Industrial & Manufacturing | AC70: 33419 | AD70: 34233 | AE70: Associate Consultant | AH70: FALSE | AI70: FALSE
A71: 321 | B71: 545 | C71: Angelo Solarino | D71: Solarino | E71: Angelo | I71: asolarin@live.com | J71: angelosolarino@gmail.com | K71: https://www.linkedin.com/ingelo-solarino-94696314/ | L71: Durham University | M71: Interior Designer | O71: Durham | Q71: Education & Research | S71: Freelance | AC71: 39508 | AD71: 40452 | AE71: Associate Consultant | AH71: FALSE | AI71: FALSE
A72: 287 | B72: 580 | C72: Anjeza Tufina | D72: Tufina | E72: Anjeza | G72: 35-40 | I72: tufina@gmail.com | M72: International Area | S72: Sales Associate & Business Development | AC72: 38860 | AD72: 39406 | AE72: Associate Consultant | AH72: FALSE | AI72: FALSE
A73: 240 | B73: 13 | C73: Anna Ambrosi | D73: Ambrosi | E73: Anna | G73: 40-45 | I73: anna.ambrosi@gmail.com | K73: https://www.linkedin.com/innaambrosi/ | L73: Frank & Faber | N73: Entry level | Q73: Other / Unclassified | R73: Anna Ambrosi Interior Design | T73: 08/2020 | V73: London | Y73: GB | AB73: Other / Unclassified | AC73: 38007 | AD73: 39469 | AE73: Associate Consultant | AH73: FALSE | AI73: FALSE
A74: 347 | B74: 48 | C74: Anna Barzanti | D74: Barzanti | E74: Anna | G74: 30-35 | I74: barzantianna@gmail.com | K74: https://www.linkedin.com/inna-barzanti | L74: Confindustria Vicenza | M74: Investment Director | N74: Entry Level | O74: Vicenza | P74: IT | Q74: Consulting & Advisory | R74: Nuove Sales | S74: Investment banking analyst | T74: 10/2018 | U74: 05/2024 | V74: Palo Alto | Y74: US | AB74: Consulting & Advisory | AC74: 40567 | AD74: 41157 | AE74: Associate Consultant | AH74: FALSE | AI74: FALSE
A75: 445 | B75: 338 | C75: Anna Latini | D75: Latini | E75: Anna | G75: 25-30 | K75: https://www.linkedin.com/inna-latini-bb8b8b128 | L75: Cvc Capital Partners | M75: Consultant | N75: C Level | O75: London | P75: GB | Q75: Financial Services | R75: Goldman Sachs | S75: Intern | T75: 06/2019 | U75: 06/2022 | V75: London | Y75: GB | AB75: Financial Services | AC75: 42886 | AE75: Associate Consultant | AH75: FALSE | AI75: FALSE
B76: 499 | C76: Anna Robbi | D76: Robbi | E76: Anna | F76: Vittoria | G76: 30-35 | I76: annavittoriarobbi@gmail.com | J76: anna_robbi@yahoo.com | K76: https://www.linkedin.com/innarobbi | L76: FE fundinfo | M76: Integration Manager | N76: Middle level | O76: London | P76: GB | Q76: Financial Services | R76: Heidrick & Struggles | S76: Manager | T76: 09/2019 | U76: 01/2023 | V76: London | Y76: GB | AB76: Consulting & Advisory | AC76: 41799 | AD76: 42534 | AE76: Secretary General | AH76: TRUE | AI76: FALSE
B77: 536 | C77: Anna Schirò | D77: Schirò | E77: Anna | F77: Claudia | G77: 25-30 | AC77: 42380 | AE77: Associate Consultant | AH77: FALSE | AI77: FALSE
B78: 558 | C78: Anna Taffarello | D78: Taffarello | E78: Anna | G78: 25-30 | I78: taffarelloa@gmail.com | K78: https://www.linkedin.com/in/anna-taffarello-a4454a251/ | L78: T8P Consulting | N78: Entry level | O78: Milan | P78: IT | Q78: Consulting & Advisory | R78: Heritage Holdings | T78: 01/2023 | U78: 01/2023 | V78: Milan | Y78: IT | AB78: Financial Services | AC78: 44571 | AD78: 45666 | AE78: President | AH78: TRUE | AI78: TRUE
A79: 33 | B79: 277 | C79: Annunziato Garofalo | D79: Garofalo | E79: Annunziato | G79: 50-55 | M79: Sales Excellence | S79: Research Assistant | AC79: 33240 | AD79: 34233 | AE79: Associate Consultant | AH79: FALSE | AI79: FALSE
A80: 191 | B80: 375 | C80: Antonella Marzorati | D80: Marzorati | E80: Antonella | G80: 40-45 | M80: Head of Consulting | S80: Junior Project Manager | AC80: 37013 | AD80: 37649 | AE80: Associate Consultant | AH80: FALSE | AI80: FALSE
A81: 273 | B81: 416 | C81: Antonino Musumeci | D81: Musumeci | E81: Antonino | G81: 40-45 | I81: musumeciantonino@gmail.com | K81: https://www.linkedin.com/intoninom/ | L81: Accenture | M81: Deputy Client Account Leader | N81: Middle Level | O81: Singapore | Q81: Consulting & Advisory | R81: Standard & Poor's | S81: General Manager Group Pricing and Value Proposition | T81: 07/2023 | U81: 05/2029 | AC81: 38732 | AD81: 39083 | AE81: Associate Consultant | AH81: FALSE | AI81: FALSE
A82: 207 | B82: 32 | C82: Antonio Attinà | D82: Attinà | E82: Antonio | G82: 40-45 | I82: antonio_attina@hotmail.com | K82: https://www.linkedin.com/intonio-attin%c3%a-pmp-389721/ | L82: BTO Research | N82: C Level | O82: Milan | P82: IT | Q82: Education & Research | R82: Barclays | T82: 01/2007 | U82: 09/2008 | V82: Milan | Y82: IT | AB82: Financial Services | AC82: 39104 | AD82: 39712 | AE82: Associate Consultant | AH82: FALSE | AI82: FALSE
A83: 219 | B83: 128 | C83: Antonio Centola | D83: Centola | E83: Antonio | G83: 40-45 | I83: antoniocentola@hotmail.com | K83: https://www.linkedin.com/intonio-centola-a8651aa/ | L83: Accenture | M83: Policy Officer | N83: C Level | O83: Sydney | P83: AU | Q83: Consulting & Advisory | R83: MTN | S83: Legal Counsel | T83: 01/2017 | U83: 01/2021 | V83: Johannesburg | Y83: ZA | AB83: Legal & Compliance | AC83: 37642 | AD83: 38860 | AE83: Secretary General | AH83: TRUE | AI83: FALSE
A84: 257 | B84: 335 | C84: Antonio Lai | D84: Lai | E84: Antonio | G84: 35-40 | I84: antonio_lai@yahoo.com | K84: https://www.linkedin.com/in/antoniolai/ | L84: European Commission | M84: IT Telecom Quality Senior Tester | N84: Middle Level | O84: Brussels | P84: BE | Q84: Public Sector & Non-Profit | R84: Qlik | S84: Owner | T84: 01/2016 | U84: 01/2018 | V84: London | Y84: GB | AB84: Legal & Compliance | AC84: 38356 | AD84: 39517 | AE84: Vice President | AH84: TRUE | AI84: FALSE
B85: 387 | C85: Antonio Maude | D85: Maude | E85: Antonio | F85: Pio | G85: 20-25 | I85: antonio.maude@icloud.com | K85: https://www.linkedin.com/in/amaude/ | L85: Bank Of America | M85: Investment Banking Summer Analyst | N85: Entry Level | O85: Cambridge | P85: US | Q85: Financial Services | AE85: Associate Consultant | AH85: FALSE | AI85: FALSE
A86: 5 | B86: 436 | C86: Antonio Oteri | D86: Oteri | E86: Antonio | G86: 60-65 | I86: antonio.oteri@gmail.com | K86: https://www.linkedin.com/in/aoteri/ | L86: Atos | M86: Managing Director | N86: C Level | O86: Sao Paulo | P86: BR | R86: Forneria Romana | S86: Assistant | T86: 01/2018 | U86: 01/2021 | V86: Sao Paulo | Y86: BR | AB86: Food & Beverage | AC86: 32464 | AD86: 33238 | AE86: Treasurer | AH86: TRUE | AI86: FALSE
A87: 200 | B87: 471 | C87: Antonio Pisu | D87: Pisu | E87: Antonio | G87: 40-45 | I87: antoniopisu@hotmail.com | K87: https://www.linkedin.com/in/antonio-pisu-3a0b463/ | L87: Mediacomm S.r.l. | M87: Forward Deployed Engineer | N87: C Level | O87: Milan | P87: IT | R87: PwC | S87: Quantitative Researcher - Credit | T87: 09/2004 | U87: 04/2006 | AB87: Consulting & Advisory | AC87: 37278 | AD87: 38007 | AE87: President | AH87: TRUE | AI87: FALSE
A88: 224 | B88: 553 | C88: Antonio Specchia | D88: Specchia | E88: Antonio | G88: 40-45 | I88: njobbaas@gmail.com | J88: antonio.specchia@fastwebnet.it / aspecchia@laneconstruct.com | K88: https://www.linkedin.com/intonio-specchia-a34622 | L88: The Lane Construction Corporation | M88: HR Director | N88: C Level | O88: Cheshire | P88: US | R88: Saipem | S88: HR Business Partner | T88: 01/2005 | U88: 08/2022 | V88: Milan | Y88: IT | AB88: Energy & Utilities | AC88: 37642 | AD88: 38007 | AE88: Treasurer | AH88: TRUE | AI88: FALSE
B89: 590 | C89: Antonio Ventura | D89: Ventura | E89: Antonio | F89: Roberto | G89: 25-30 | K89: https://www.linkedin.com/in/antoniorventura/ | L89: H Company | M89: General Manager | N89: Middle Level | O89: Paris | P89: FR | Q89: Technology & Software | R89: BNP Paribas | S89: Business Administration Manager | T89: 04/2025 | U89: 11/2025 | V89: London | Y89: GB | AB89: Financial Services | AC89: 44105 | AD89: 44256 | AE89: Associate Consultant | AH89: FALSE | AI89: FALSE
A90: 254 | B90: 598 | C90: Antonio Volpone | D90: Volpone | E90: Antonio | G90: 40-45 | I90: antonio.volpone@gmail.com | K90: https://www.linkedin.com/intonio-volpone-8bb4b | L90: Ater Fondazione | M90: Governance and Communications Manager | N90: Middle Level | O90: Modena | Q90: Media, Marketing & Entertainment | R90: Ente Mostra Internazionale del Cinema Libero | S90: Head of Bid Management | T90: 06/2013 | U90: 02/2018 | V90: Bologna | Y90: IT | AB90: Media, Marketing & Entertainment | AC90: 38356 | AD90: 38858 | AE90: Associate Consultant | AH90: FALSE | AI90: FALSE
A91: 116 | B91: 342 | C91: Arianna Libratti | D91: Libratti | E91: Arianna | G91: 45-50 | I91: arianna.libratti@sinsys.net | K91: https://www.linkedin.com/in/arianna-libratti-5773396/ | L91: Nexi Group | M91: Senior Learning Analyst | N91: Middle Level | O91: Milan | P91: IT | Q91: Financial Services | R91: SIA S.p.A. | S91: Summer Intern | T91: 04/2013 | U91: 01/2018 | V91: Milan | Y91: IT | AB91: Technology & Software | AC91: 35488 | AD91: 37313 | AE91: Head of HR | AH91: FALSE | AI91: TRUE
A92: 523 | B92: 68 | C92: Armando Bianchimano | D92: Bianchimano | E92: Armando | G92: 25-30 | I92: armandobianchimano@gmail.com | K92: https://www.linkedin.com/in/armandobianchimano/ | L92: BPI Learn | M92: Product Manager | N92: Middle level | O92: Madrid | P92: ES | Q92: Consulting & Advisory | R92: Accenture | S92: Consultant | T92: 01/2022 | U92: 01/2022 | V92: Milan | Y92: IT | AB92: Financial Services | AC92: 43836 | AD92: 44928 | AE92: Associate Consultant | AH92: FALSE | AI92: FALSE
A93: 381 | B93: 135 | C93: Armando Cianci | D93: Cianci | E93: Armando | G93: 25-30 | I93: armandocianci1@gmail.com | K93: https://www.linkedin.com/irmandocianci | L93: Assist Digital | N93: Middle Level | O93: Milan | P93: IT | Q93: Technology & Software | R93: Innext | T93: 01/2017 | U93: 01/2019 | V93: Milan | Y93: IT | AB93: Consulting & Advisory | AC93: 41792 | AD93: 42162 | AE93: Associate Consultant | AH93: FALSE | AI93: FALSE
A94: 332 | B94: 195 | C94: Armando Del Vecchio | D94: Del Vecchio | E94: Armando | G94: 35-40 | I94: armando.delvecchioat@gmail.com | M94: Controller for reporting Pon projects | S94: Consultant | AC94: 40323 | AD94: 41533 | AE94: President of JADE | AF94: Treasurer | AH94: TRUE | AI94: FALSE
A95: 276 | B95: 186 | C95: Attilio De Luca | D95: De Luca | E95: Attilio | G95: 35-40 | I95: agdeluca@unict.it | J95: attilio_de@yahoo.it | K95: https://www.linkedin.com/in/attilio-de-luca-76a1757/ | L95: Università di Catania | M95: Business Development & Strategy Manager | N95: Middle Level | O95: Catania | P95: IT | Q95: Education & Research | R95: EY | T95: 07/2011 | U95: 12/2013 | V95: Milan | Y95: IT | AB95: Consulting & Advisory | AC95: 38797 | AD95: 39083 | AE95: Associate Consultant | AH95: FALSE | AI95: FALSE
A96: 518 | B96: 564 | C96: Aurelio Tempesta | D96: Tempesta | E96: Aurelio | G96: 25-30 | I96: aureliotempesta00@gmail.com | K96: https://www.linkedin.com/in/aureliotempesta/ | L96: HIOP | M96: Private Equity Associate | N96: Middle Level | O96: Milan | P96: IT | Q96: Technology & Software | S96: Investment Banking Intern | AC96: 43843 | AD96: 45093 | AE96: President | AF96: Head of IT | AG96: Secretary General | AH96: TRUE | AI96: TRUE
A97: 461 | B97: 575 | C97: Aurora Trentini | D97: Trentini | E97: Aurora | G97: 25-30 | I97: aurora.trentini@gmail.com | K97: https://www.linkedin.com/iurora-trentini-448727157/ | L97: Blackstone | M97: Co-Founder | N97: Middle Level | O97: London | P97: GB | Q97: Financial Services | R97: J.P. Morgan | S97: Senior Manager | T97: 01/2021 | U97: 01/2021 | V97: London | Y97: GB | AB97: Financial Services | AC97: 43115 | AD97: 43830 | AE97: Associate Consultant | AH97: FALSE | AI97: FALSE
A98: 236 | B98: 294 | C98: Azzurra Giorgio | D98: Giorgio | E98: Azzurra | G98: 40-45 | I98: azzurra.giorgio@gmail.com | K98: https://www.linkedin.com/izzurragiorgio | L98: Intervieweb | M98: Executive Chairman | N98: C Level | O98: Turin | P98: IT | Q98: Technology & Software | R98: Exton Consulting | S98: COO and Deputy CEO | T98: 01/2014 | U98: 01/2022 | V98: Milan | Y98: IT | AB98: Consulting & Advisory | AC98: 37797 | AD98: 39813 | AE98: Vice President | AH98: TRUE | AI98: FALSE
A99: 24 | B99: 147 | C99: Barbara Cominelli | D99: Cominelli | E99: Barbara | G99: 50-55 | I99: barbara.cominelli@gmail.com | K99: https://www.linkedin.com/in/barbaracominelli/ | L99: Spindox | N99: C Level | O99: Milan | P99: IT | Q99: Technology & Software | R99: Microsoft | T99: 03/2018 | U99: 01/2020 | V99: Milan | Y99: IT | AB99: Technology & Software | AC99: 33240 | AD99: 34236 | AE99: Administrator | AH99: TRUE | AI99: FALSE
A100: 90 | B100: 271 | C100: Barbara Garavaglia | D100: Garavaglia | E100: Barbara | G100: 50-55 | M100: CEO | S100: Director | AC100: 34236 | AD100: 34347 | AE100: Associate Consultant | AH100: FALSE | AI100: FALSE
...

Sheet People to contact
B2: Contact | C2: Surname | D2: Name | E2: LinkedIn | F2: Proj | G2: JEME4U | H2: Contacted | I2: Positive Answer | J2: Negative Answer | K2: Notes
B3: Maria | C3: Nichil | D3: =_xlfn.XLOOKUP('People to contact'!C3,#REF!,#REF!) -> #REF! | E3: https://www.linkedin.com/in/matteo-nichil-6b9189b/ | F3: x | H3: x
B4: Maria | C4: Almiento | D4: =_xlfn.XLOOKUP('People to contact'!C4,#REF!,#REF!) -> #REF! | E4: https://www.linkedin.com/in/giancarlo-almiento-951831/ | G4: x | H4: x
B5: Gio | C5: Benintende | D5: =_xlfn.XLOOKUP('People to contact'!C5,#REF!,#REF!) -> #REF! | E5: https://www.linkedin.com/in/francesco-benintende-4721a3 | G5: x | H5: x
C6: Brentel | D6: =_xlfn.XLOOKUP('People to contact'!C6,#REF!,#REF!) -> #REF! | E6: https://www.linkedin.com/in/stefano-brentel-4ba6a2 | G6: x | K6: do after Bain event
B7: Maria | C7: Cherubini | D7: =_xlfn.XLOOKUP('People to contact'!C7,#REF!,#REF!) -> #REF! | E7: https://www.linkedin.com/in/gianandrea-cherubini-82a431 | F7: x | G7: x | H7: x
B8: Gio | C8: Grabstein | D8: =_xlfn.XLOOKUP('People to contact'!C8,#REF!,#REF!) -> #REF! | E8: https://www.linkedin.com/in/simon-grabstein-a8425b/ | F8: x | H8: x
B9: Maria | C9: Lazzari | D9: =_xlfn.XLOOKUP('People to contact'!C9,#REF!,#REF!) -> #REF! | E9: https://www.linkedin.com/in/andrea-lazzari-94158519/ | F9: x | H9: x
B10: Maria | C10: Matuozzo | D10: =_xlfn.XLOOKUP('People to contact'!C10,#REF!,#REF!) -> #REF! | E10: https://www.linkedin.com/ilberto-matuozzo-2a54a8 | F10: x | H10: x
B11: Maria | C11: Pierantozzi | D11: =_xlfn.XLOOKUP('People to contact'!C11,#REF!,#REF!) -> #REF! | E11: https://www.linkedin.com/in/david-pierantozzi-0a44a5b/ | F11: x | H11: x
B12: Maria | C12: Alloisio | D12: =_xlfn.XLOOKUP('People to contact'!C12,#REF!,#REF!) -> #REF! | E12: https://www.linkedin.com/ilessandro-alloisio-9a13a/ | F12: x | H12: x
B13: Maria | C13: Benedetti del Rio | D13: =_xlfn.XLOOKUP('People to contact'!C13,#REF!,#REF!) -> #REF! | E13: https://www.linkedin.com/in/roberta-benedetti-del-rio-7a957b14/ | F13: x | H13: x
B14: Gio | C14: Benini | D14: =_xlfn.XLOOKUP('People to contact'!C14,#REF!,#REF!) -> #REF! | E14: https://www.linkedin.com/in/stefano-benini/ | F14: x | H14: x
B15: Maria | C15: Biancolin | D15: =_xlfn.XLOOKUP('People to contact'!C15,#REF!,#REF!) -> #REF! | E15: https://www.linkedin.com/in/michele-biancolin-863161/ | G15: x | H15: x
B16: Maria | C16: Bressan | D16: =_xlfn.XLOOKUP('People to contact'!C16,#REF!,#REF!) -> #REF! | E16: https://www.linkedin.com/ilessio-bressan-8b26b/ | F16: x | H16: x
B17: Maria | C17: Casati | D17: =_xlfn.XLOOKUP('People to contact'!C17,#REF!,#REF!) -> #REF! | E17: https://www.linkedin.com/in/stefano-casati-524b421/ | F17: x | H17: x
B18: Maria | C18: Cionini Visani | D18: =_xlfn.XLOOKUP('People to contact'!C18,#REF!,#REF!) -> #REF! | E18: https://www.linkedin.com/in/camilla-cionini-visani-581aa3/ | F18: x | H18: x
B19: Maria | C19: Conzi | D19: =_xlfn.XLOOKUP('People to contact'!C19,#REF!,#REF!) -> #REF! | E19: https://www.linkedin.com/in/giovanna-conzi-39a657/ | F19: x | H19: x
B20: Maria | C20: Del Grande | D20: =_xlfn.XLOOKUP('People to contact'!C20,#REF!,#REF!) -> #REF! | E20: https://www.linkedin.com/in/giacomodelgrande | F20: x | H20: x
B21: Gio | C21: Esentato | D21: =_xlfn.XLOOKUP('People to contact'!C21,#REF!,#REF!) -> #REF! | E21: https://www.linkedin.com/in/maurizio-g-esentato-922528a/ | F21: x | H21: x
C22: Fabbrini | D22: =_xlfn.XLOOKUP('People to contact'!C22,#REF!,#REF!) -> #REF! | E22: https://www.linkedin.com/in/francescofabbrini | G22: x | H22: x
C23: Fedel | D23: =_xlfn.XLOOKUP('People to contact'!C23,#REF!,#REF!) -> #REF! | E23: https://www.linkedin.com/in/fabiofedel/ | G23: x | H23: x
B24: Gio | C24: Fenaroli | D24: =_xlfn.XLOOKUP('People to contact'!C24,#REF!,#REF!) -> #REF! | E24: https://www.linkedin.com/in/fenarolimatteo | F24: x | H24: x
B25: Luca | C25: Ferrario | D25: =_xlfn.XLOOKUP('People to contact'!C25,#REF!,#REF!) -> #REF! | E25: https://www.linkedin.com/in/michele-ferrario-a464211/ | F25: x
B26: Maria | C26: Franchetti | D26: =_xlfn.XLOOKUP('People to contact'!C26,#REF!,#REF!) -> #REF! | E26: =_xlfn.XLOOKUP('People to contact'!C26,#REF!,#REF!) -> #REF! | F26: x | H26: x
C27: Galeandro | D27: =_xlfn.XLOOKUP('People to contact'!C27,#REF!,#REF!) -> #REF! | E27: =_xlfn.XLOOKUP('People to contact'!C27,#REF!,#REF!) -> #REF! | G27: x | H27: x
C28: Gardella | D28: =_xlfn.XLOOKUP('People to contact'!C28,#REF!,#REF!) -> #REF! | E28: =_xlfn.XLOOKUP('People to contact'!C28,#REF!,#REF!) -> #REF! | H28: x
B29: Gio | C29: Garosio | D29: =_xlfn.XLOOKUP('People to contact'!C29,#REF!,#REF!) -> #REF! | E29: =_xlfn.XLOOKUP('People to contact'!C29,#REF!,#REF!) -> #REF! | F29: x | H29: x
B30: Maria | C30: Giorgio | D30: =_xlfn.XLOOKUP('People to contact'!C30,#REF!,#REF!) -> #REF! | E30: =_xlfn.XLOOKUP('People to contact'!C30,#REF!,#REF!) -> #REF! | F30: x | H30: x
C31: Mariani | D31: =_xlfn.XLOOKUP('People to contact'!C31,#REF!,#REF!) -> #REF! | E31: =_xlfn.XLOOKUP('People to contact'!C31,#REF!,#REF!) -> #REF! | G31: x | H31: x
B32: Gio | C32: Mauri | D32: =_xlfn.XLOOKUP('People to contact'!C32,#REF!,#REF!) -> #REF! | E32: =_xlfn.XLOOKUP('People to contact'!C32,#REF!,#REF!) -> #REF! | F32: x | H32: x
B33: Gio | C33: Mento | D33: =_xlfn.XLOOKUP('People to contact'!C33,#REF!,#REF!) -> #REF! | E33: =_xlfn.XLOOKUP('People to contact'!C33,#REF!,#REF!) -> #REF! | F33: x | H33: x
B34: Gio | C34: Miglioranzi | D34: =_xlfn.XLOOKUP('People to contact'!C34,#REF!,#REF!) -> #REF! | E34: =_xlfn.XLOOKUP('People to contact'!C34,#REF!,#REF!) -> #REF! | F34: x | H34: x
C35: Moncalvo | D35: =_xlfn.XLOOKUP('People to contact'!C35,#REF!,#REF!) -> #REF! | E35: =_xlfn.XLOOKUP('People to contact'!C35,#REF!,#REF!) -> #REF! | F35: x | H35: x
B36: Maria | C36: Neytcheva | D36: =_xlfn.XLOOKUP('People to contact'!C36,#REF!,#REF!) -> #REF! | E36: =_xlfn.XLOOKUP('People to contact'!C36,#REF!,#REF!) -> #REF! | F36: x | H36: x | K36: To text in Bulgarian
B37: Gio | C37: Nuebling | D37: =_xlfn.XLOOKUP('People to contact'!C37,#REF!,#REF!) -> #REF! | E37: =_xlfn.XLOOKUP('People to contact'!C37,#REF!,#REF!) -> #REF! | F37: x | H37: x
B38: Gio | C38: Palacino | D38: =_xlfn.XLOOKUP('People to contact'!C38,#REF!,#REF!) -> #REF! | E38: =_xlfn.XLOOKUP('People to contact'!C38,#REF!,#REF!) -> #REF! | F38: x | H38: x
B39: Gio | C39: Podestà | D39: =_xlfn.XLOOKUP('People to contact'!C39,#REF!,#REF!) -> #REF! | E39: =_xlfn.XLOOKUP('People to contact'!C39,#REF!,#REF!) -> #REF! | F39: x | H39: x
B40: Gio | C40: Puddu | D40: =_xlfn.XLOOKUP('People to contact'!C40,#REF!,#REF!) -> #REF! | E40: =_xlfn.XLOOKUP('People to contact'!C40,#REF!,#REF!) -> #REF! | F40: x | H40: x
B41: Gio | C41: Puglisi | D41: =_xlfn.XLOOKUP('People to contact'!C41,#REF!,#REF!) -> #REF! | E41: =_xlfn.XLOOKUP('People to contact'!C41,#REF!,#REF!) -> #REF! | F41: x | H41: x
B42: Gio | C42: Radaelli | D42: =_xlfn.XLOOKUP('People to contact'!C42,#REF!,#REF!) -> #REF! | E42: =_xlfn.XLOOKUP('People to contact'!C42,#REF!,#REF!) -> #REF! | F42: x | H42: x
B43: Gio | C43: Raimondi | D43: =_xlfn.XLOOKUP('People to contact'!C43,#REF!,#REF!) -> #REF! | E43: =_xlfn.XLOOKUP('People to contact'!C43,#REF!,#REF!) -> #REF! | F43: x | H43: x
B44: Gio | C44: Regeni | D44: =_xlfn.XLOOKUP('People to contact'!C44,#REF!,#REF!) -> #REF! | E44: =_xlfn.XLOOKUP('People to contact'!C44,#REF!,#REF!) -> #REF! | F44: x | H44: x
B45: Gio | C45: Sorgi | D45: =_xlfn.XLOOKUP('People to contact'!C45,#REF!,#REF!) -> #REF! | E45: =_xlfn.XLOOKUP('People to contact'!C45,#REF!,#REF!) -> #REF! | F45: x | H45: x
B46: Gio | C46: Zannini | D46: =_xlfn.XLOOKUP('People to contact'!C46,#REF!,#REF!) -> #REF! | E46: =_xlfn.XLOOKUP('People to contact'!C46,#REF!,#REF!) -> #REF! | F46: x | H46: x
B47: Gio | C47: Zhang | D47: =_xlfn.XLOOKUP('People to contact'!C47,#REF!,#REF!) -> #REF! | E47: =_xlfn.XLOOKUP('People to contact'!C47,#REF!,#REF!) -> #REF! | F47: x | H47: x
B48: Gio | C48: Bandini | D48: =_xlfn.XLOOKUP('People to contact'!C48,#REF!,#REF!) -> #REF! | E48: =_xlfn.XLOOKUP('People to contact'!C48,#REF!,#REF!) -> #REF! | F48: x | H48: x
... B76: Maria | C76: Marchese | D76: =_xlfn.XLOOKUP('People to contact'!C76,#REF!,#REF!) -> #REF! | E76: =_xlfn.XLOOKUP('People to contact'!C76,#REF!,#REF!) -> #REF! | F76: x | H76: x
D77: =_xlfn.XLOOKUP('People to contact'!C77,#REF!,#REF!) -> #REF! | E77: =_xlfn.XLOOKUP('People to contact'!C77,#REF!,#REF!) -> #REF!
D78: =_xlfn.XLOOKUP('People to contact'!C78,#REF!,#REF!) -> #REF! | E78: =_xlfn.XLOOKUP('People to contact'!C78,#REF!,#REF!) -> #REF!
D79: =_xlfn.XLOOKUP('People to contact'!C79,#REF!,#REF!) -> #REF! | E79: =_xlfn.XLOOKUP('People to contact'!C79,#REF!,#REF!) -> #REF!
D80: =_xlfn.XLOOKUP('People to contact'!C80,#REF!,#REF!) -> #REF! | E80: =_xlfn.XLOOKUP('People to contact'!C80,#REF!,#REF!) -> #REF!
D81: =_xlfn.XLOOKUP('People to contact'!C81,#REF!,#REF!) -> #REF! | E81: =_xlfn.XLOOKUP('People to contact'!C81,#REF!,#REF!) -> #REF!
D82: =_xlfn.XLOOKUP('People to contact'!C82,#REF!,#REF!) -> #REF! | E82: =_xlfn.XLOOKUP('People to contact'!C82,#REF!,#REF!) -> #REF!
D83: =_xlfn.XLOOKUP('People to contact'!C83,#REF!,#REF!) -> #REF! | E83: =_xlfn.XLOOKUP('People to contact'!C83,#REF!,#REF!) -> #REF!
D84: =_xlfn.XLOOKUP('People to contact'!C84,#REF!,#REF!) -> #REF! | E84: =_xlfn.XLOOKUP('People to contact'!C84,#REF!,#REF!) -> #REF!
D85: =_xlfn.XLOOKUP('People to contact'!C85,#REF!,#REF!) -> #REF! | E85: =_xlfn.XLOOKUP('People to contact'!C85,#REF!,#REF!) -> #REF!
C86: Castellano | D86: =_xlfn.XLOOKUP('People to contact'!C86,#REF!,#REF!) -> #REF! | E86: =_xlfn.XLOOKUP('People to contact'!C86,#REF!,#REF!) -> #REF! | H86: x
F88: =COUNTA(F3:F75) -> 64 | G88: =COUNTA(G3:G75) -> 9 | H88: =COUNTA(H3:H75) -> 71

Sheet TMP
A1: Full Name | B1: First Name | C1: Middle Name(s) | D1: Second Name(s) | E1: E-mail Address | F1: E-mail Address #2 | G1: Mobile Phone #1 | H1: Mobile Phone #2 | I1: LinkedIn | J1: Firm #1 | K1: Role #1 | L1: Starting Month #1 | M1: Ending Month #1 | N1: Location #1 | O1: Industry #1 | P1: Firm #2 | Q1: Role #2 | R1: Starting Month #2 | S1: Ending Month #2 | T1: Location #2 | U1: Industry #2 | V1: JEME - Starting Period | W1: JEME - Ending Period | X1: JEME - Role #1 | Y1: JEME - Role #2 | Z1: JEME - Role #3
A2: Agnieszka Kania | B2: Agnieszka | D2: Kania | E2: lesniewska.agnieszka@gmail.com | I2: https://www.linkedin.com/agnieszkadariakania/ | J2: GSK | K2: Service Desk Manager | L2: 39722 | M2: 40148 | N2: Milan, Italy | O2: Pharmaceutical | P2: dotOne | Q2: Business Analyst | R2: 40911 | S2: 41279 | U2: Technology | X2: Associate Consultant
A3: Alberto Accogli | B3: Alberto | D3: Accogli | E3: alberto.accogli@gmail.com | G3: +39 328 628229 | I3: https://www.linkedin.com/alberto-accogli/ | J3: Amazon | K3: MBA Summer Intern | L3: 38626 | M3: 40513 | N3: Milan, Italy | O3: Retail | P3: Leoni Corporate Advisors | Q3: Junior Manager | R3: 40913 | S3: 43470 | U3: Consulting | V3: 38732 | W3: 39447 | X3: Secretary General
A4: Alberto Antoniolli | B4: Alberto | D4: Antoniolli | E4: alberto.antoniolli@gmail.com | G4: +39 342 6423569 | I4: https://www.linkedin.com/albertoantoniolli/ | J4: Lazard | K4: M&A Analyst | L4: 43497 | M4: 44896 | N4: Milan, Italy | O4: Advisory | P4: Italmobiliare SPA | Q4: Intern Financial Analyst | R4: 44202 | S4: 43474 | T4: Milan, Italy | U4: Investments | V4: 43626 | W4: 44743 | X4: Treasurer
A5: Alberto Cattaruzza | B5: Alberto | D5: Cattaruzza | E5: cattaruzza98@gmail.com | I5: https://www.linkedin.com/alberto-cattaruzza-84a1a196/ | J5: Bank of America | K5: Investment Banking Analyst | L5: 43891 | M5: 44470 | N5: Milan, Italy | O5: Investment Banking | P5: Italian Angels for Growth | R5: 43472 | S5: 43472 | T5: Milan, Italy | U5: Investments | X5: Associate Consultant
A6: Alberto Franco | B6: Alberto | D6: Franco | E6: alberto.franco@cbalex.com | G6: +39 348 862155 | I6: https://www.linkedin.com/albertofrancoit | J6: CBA Studio Legale e Tributario | N6: Milan, Italy | O6: Legal | P6: Università degli Studi di Torino | Q6: Professore a contratto | R6: 42005 | T6: Turin | U6: Education | X6: Associate Consultant
A7: Alberto Holler | B7: Alberto | D7: Holler | E7: alberto.holler@gmail.com | G7: +39 345 7151799 | I7: https://www.linkedin.com/alberto-holler-72a95199/ | J7: Generali | K7: M&A Analyst | L7: 43831 | M7: 44593 | N7: Milan, Italy | O7: Banking | P7: Deloitte | Q7: Summer Intern | R7: 44202 | S7: 44205 | T7: Milan, Italy | U7: Consulting | V7: 43843 | W7: 44627 | X7: Secretary General | Y7: Head of Internal Audit | Z7: Project Manager
A8: Alberto Matuozzo | B8: Alberto | D8: Matuozzo | E8: alberto_matuozzo@yahoo.co.uk | G8: +44 7919447118 | I8: https://www.linkedin.com/alberto-matuozzo-2a54a8 | J8: Farema Capital | K8: Partner | L8: 33970 | M8: 36160 | N8: London, United Kingdom | O8: Investment Banking | P8: Merian Capital LLP | Q8: Partner | R8: 44927 | S8: 40909 | U8: Investments | V8: 35104 | W8: 35766 | X8: Associate Consultant
A9: Alberto Vedovi | B9: Alberto | D9: Vedovi | E9: vedovia@gmail.com | I9: https://www.linkedin.com/alberto-vedovi-48832772 | J9: NS PARTNERS | L9: 42095 | M9: 43009 | N9: Luxemburg | O9: Private Equity | P9: Deloitte | Q9: Consultant | R9: 43472 | S9: 44570 | T9: Luxemburg | U9: Consulting | V9: 42159 | W9: 43059 | X9: Vice President | Y9: Tresaurer
A10: Aldo Pozzoli | B10: Aldo | D10: Pozzoli | E10: aldopozzoli@hotmail.com | I10: https://www.linkedin.com/aldopozzoli/ | J10: Accenture | K10: Principal Director | L10: 38353 | M10: 38353 | N10: Milan, Italy | O10: Consulting | P10: Comune di Milano | Q10: Consultant | R10: 44930 | S10: 40547 | T10: Milan, Italy | U10: Public Policy | V10: 36871 | W10: 37649 | X10: Associate Consultant
A11: Alessandra Arrigoni | B11: Alessandra | D11: Arrigoni | E11: alessandraarrigoni@hotmail.com | I11: https://www.linkedin.com/alessandra-arrigoni-8aa45b7/ | J11: NielsenIQ | K11: Client Business Partner | N11: London, United Kingdom | O11: Technology | P11: Nielsen | Q11: Consultant | R11: 44929 | S11: 42009 | T11: London, United Kingdom | U11: Technology | V11: 37642 | W11: 38007 | X11: Associate Consultant
A12: Alessandra Galli | B12: Alessandra | D12: Galli | E12: ale.galli76@gmail.com | G12: +39 347 73663 | V12: 35831 | W12: 35990 | X12: Associate Consultant
A13: Alessandra Mangeri | B13: Alessandra | D13: Mangeri | E13: ale.mangeri@virgilio.it | I13: https://www.linkedin.com/alessandra-mangeri-656893b/ | J13: AMG | K13: Tax Advisor | L13: 34335 | M13: 34335 | O13: Accounting | P13: Tribunale di Brescia | Q13: Advisor | R13: 40544 | T13: Brescia | U13: Advisory | V13: 33865 | W13: 37315 | X13: Associate Consultant
A14: Alessandra Peres | B14: Alessandra | D14: Peres | G14: +39 349 7865587 | I14: https://www.linkedin.com/alessandra-peres-21b2a2b/ | J14: Swiss Re Corporate Solutions | K14: Distribution Manager | L14: 39142 | M14: 40513 | N14: Milan, Italy | P14: FC Rimaco | Q14: Area Manager | R14: 44562 | S14: 44927 | T14: Lugano | U14: Insurance | V14: 39329 | W14: 40513 | X14: Associate Consultant
A15: Alessandra Vultaggio | B15: Alessandra | D15: Vultaggio | E15: alexvulty@gmail.com | G15: +39 349 4753351 | I15: https://www.linkedin.com/alessandravultaggio/ | J15: Global Blue | K15: Customer Value Creation Manager | L15: 35065 | M15: 37256 | N15: Milan, Italy | O15: Investments | P15: Edenred Italia | Q15: Director | R15: 40548 | S15: 43476 | T15: Milan, Italy | U15: Financial Services | V15: 35831 | W15: 37298 | X15: Associate Consultant
A16: Alessandro Alloisio | B16: Alessandro | D16: Alloisio | G16: +39 335 6843375 | I16: https://www.linkedin.com/alessandro-alloisio-9a13a/ | J16: Sanlorenzo Yacht | K16: Chief Information Officer | L16: 32874 | M16: 35064 | N16: Ameglia | O16: Construction | Q16: Freelancer | R16: 44564 | S16: 44197 | T16: Como | V16: 32464 | W16: 34233 | X16: Associate Consultant
A17: Alessandro Bellotti | B17: Alessandro | D17: Bellotti | V17: 32464 | W17: 33238 | X17: Associate Consultant
A18: Alessandro Brambilla | B18: Alessandro | D18: Brambilla | V18: 33419 | W18: 34466 | X18: Associate Consultant
A19: Alessandro Brutto | B19: Alessandro | D19: Brutto | E19: bruttoalessandro@gmail.com | G19: +39 338 7388 | I19: https://www.linkedin.com/alessandro-brutto-bb15117 | J19: Goldman Sachs | K19: Associate | L19: 42430 | M19: 42795 | N19: London, United Kingdom | O19: Investment Banking | P19: JP Morgan | Q19: Analyst | R19: 43471 | S19: 44197 | T19: London, United Kingdom | U19: Investment Banking | V19: 42513 | W19: 42790 | X19: Associate Consultant
A20: Alessandro Dadone | B20: Alessandro | D20: Dadone | E20: ale.dadone@gmail.com | I20: https://www.linkedin.com/alessandro-dadone-23196318 | J20: Casavo | K20: Head of Product | L20: 42614 | M20: 43466 | N20: Milan, Italy | O20: Investments | P20: Coca-Cola | Q20: Customer Marketing Intern | R20: 43106 | S20: 43109 | T20: Athens | U20: Food & Beverage | V20: 42751 | W20: 43472 | X20: Vice President
A21: Alessandro Filoramo | B21: Alessandro | D21: Filoramo | E21: alessandro.filoram@gmail.com | I21: https://www.linkedin.com/alessandrofiloramo | J21: Arthur D. Little | K21: Consultant | L21: 42614 | M21: 43497 | N21: Dubai | O21: Consulting | P21: IQVIA | Q21: Analyst | R21: 44570 | S21: 44203 | T21: Milan, Italy | X21: President
A22: Alessandro Gagliardi | B22: Alessandro | D22: Gagliardi | I22: https://www.linkedin.com/alessandro-gagliardi/ | J22: GE Capital | K22: Vice-President | L22: 44932 | M22: 42376 | N22: London, United Kingdom | O22: Banking | V22: 37013 | W22: 37298 | X22: Associate Consultant
A23: Alessandro Medico | B23: Alessandro | D23: Medico | E23: alemedi@icloud.com | I23: https://www.linkedin.com/alessandro-medico/ | J23: Amazon | K23: Intern | L23: 43709 | M23: 44573 | N23: Luxemburg | O23: Retail | P23: Bending Spoons | Q23: M&A Intern | R23: 44197 | S23: 44565 | T23: Milan, Italy | U23: Technology | V23: 43843 | X23: Associate Consultant
A24: Alessandro Radici | B24: Alessandro | D24: Radici | E24: alessandro.radici@seragro.com.ar | G24: 973 6522374 | H24: 9 2664 957555 | I24: https://www.linkedin.com/alessandro-radici-9988317/ | J24: SER BEEF | K24: President | L24: 38718 | M24: 39082 | N24: San Luis | O24: Consulting | P24: McKinsey & Company | R24: 40916 | S24: 42011 | T24: New Jersey | U24: Consulting | V24: 38356 | W24: 39083 | X24: Associate Consultant
A25: Alessandro Trisciuoglio | B25: Alessandro | D25: Trisciuoglio | E25: aletrisc@gmail.com | I25: https://www.linkedin.com/alessandro-trisciuoglio/ | J25: Booking.com | K25: Self Employed | L25: 44197 | M25: 44805 | N25: Diano Marina | P25: Beko | Q25: Intern | R25: 44563 | S25: 44928 | T25: Milan, Italy | U25: Consumer Goods | X25: Associate Consultant
A26: Alessia Acquistapace | B26: Alessia | D26: Acquistapace | I26: https://www.linkedin.com/alessia-acquistapace-22972165/ | J26: Amazon | K26: Financial Analyst | L26: 42979 | M26: 44835 | N26: Luxemburg | O26: Retail | P26: Rothshild & Co. | Q26: Intern | R26: 44202 | S26: 44197 | T26: Milan, Italy | U26: Investment Banking | V26: 43255 | X26: Associate Consultant
A27: Alessia Alberti | B27: Alessia | D27: Alberti | E27: alessia.alberti96@gmail.com | I27: https://www.linkedin.com/alessia-alberti-b75a612b/ | J27: Roveda Laurini Clerici D’Amore Notai | K27: Praticante Notaio | L27: 43252 | M27: 43862 | N27: Milan, Italy | O27: Legal | P27: Bonelli Erede | Q27: Praticante Avvocato | R27: 44563 | S27: 44568 | T27: Milan, Italy | U27: Legal | V27: 43255 | W27: 43871 | X27: Associate Consultant
A28: Alessia Della Vedova | B28: Alessia | D28: Della Vedova | G28: +39 338 272557 | I28: https://www.linkedin.com/alessia-dellavedova/ | J28: Russo De Rosa Associati | K28: Dottore Commercialista - Revisore Legale | L28: 33970 | M28: 36160 | O28: Legal | P28: Fieldfisher - Studio Associato Servizi Professionali Integrati | Q28: Dottore Commercialista - Revisore Legale | R28: 43102 | S28: 43473 | T28: Milan, Italy | U28: Legal | V28: 35831 | W28: 36121 | X28: Associate Consultant
A29: Alessia Fontanari | B29: Alessia | D29: Fontanari | E29: alessia.fon@gmail.com | I29: https://www.linkedin.com/alessiafontanari | J29: Doctolib | K29: Strategy Manager | L29: 41275 | M29: 42401 | N29: Milan, Italy | O29: Medical/Healthcare | P29: McKinsey & Company | Q29: Associate | R29: 44197 | S29: 44208 | T29: Milan, Italy | U29: Consulting | V29: 41310 | W29: 42499 | X29: Head of Sales
A30: Alessio Bressan | B30: Alessio | D30: Bressan | E30: alessio.bressan@igbressan.it | I30: https://www.linkedin.com/alessio-bressan-8b26b/ | J30: IGB - Industrie Grafiche Bressan | K30: CEO | L30: 33604 | M30: 36160 | N30: Milan, Italy | O30: Retail | P30: EY | Q30: Consultant | S30: 1/1/1099 | U30: Consulting | V30: 35488 | W30: 35766 | X30: Associate Consultant
A31: Alessio Fortunato Ficara | B31: Alessio | C31: Fortunato | D31: Ficara | E31: alessioficara@gmail.com | I31: https://www.linkedin.com/alessiofortunatoficara/ | J31: La Maison - la tua casa su misura | K31: Titolare | L31: 34700 | M31: 36891 | N31: Milan, Italy | O31: Retail | P31: Jobseeker | Q31: Manager | R31: 43101 | U31: Technology | V31: 35831 | W31: 37298 | X31: Associate Consultant
A32: Alessio Loreti | B32: Alessio | D32: Loreti | G32: +39 347 351471 | V32: 35831 | W32: 36121 | X32: Associate Consultant
A33: Alex Cecchini | B33: Alex | D33: Cecchini | E33: alex.cecchini@me.com | I33: https://www.linkedin.com/alex-cecchini-579278/ | J33: Bank J. Safra Sarasin Ltd | K33: Executive Director | L33: 32509 | M33: 34699 | N33: Lugano | O33: Banking | P33: LGT – Private Banking und Asset Management | Q33: Managing Director | R33: 43471 | S33: 44562 | T33: Lugano | U33: Banking | V33: 34236 | W33: 34347 | X33: Associate Consultant
A34: Alex Fattorini | B34: Alex | D34: Fattorini | G34: +39 338 7775421 | I34: https://www.linkedin.com/alex-fattorini-263999/ | J34: Primonial Reim Italy | K34: Member of Boad of Directors | L34: 36161 | M34: 36526 | N34: Milan, Italy | P34: DGPA & Co. | Q34: Partner | R34: 42744 | T34: Milan, Italy | U34: Consulting | V34: 36280 | W34: 36584 | X34: Associate Consultant
A35: Alice Zarantonello | B35: Alice | D35: Zarantonello | E35: alicezarantonello@outlook.com | I35: https://www.linkedin.com/alice-zarantonello/ | J35: McKinsey & Company | K35: Junior Associate | L35: 43221 | M35: 43739 | N35: Milan, Italy | O35: Consulting | P35: Microsoft | Q35: Product Marketing Manager | R35: 44198 | S35: 44570 | T35: Milan, Italy | U35: Technology | V35: 43255 | W35: 43774 | X35: Associate Consultant
A36: Alvise Biffi | B36: Alvise | D36: Biffi | E36: a.biffi@securenetwork.it | G36: +39 338 9925329 | I36: https://www.linkedin.com/alvise-biffi-115aa5/ | J36: Secure Network Srl | K36: CEO | L36: 36161 | M36: 36861 | N36: Milan, Italy | O36: Technology | P36: Assolombarda | Q36: Vicepresidente | R36: 44930 | T36: Milan, Italy | U36: Public Policy | V36: 36280 | W36: 37649 | X36: President
A37: Amin Harbi | B37: Amin | D37: Harbi | E37: aharbi13@gmail.com | I37: https://www.linkedin.com/amin-harbi/ | J37: Boston Consulting Group | K37: Intern | L37: 43374 | M37: 44713 | N37: Milan, Italy | O37: Consulting | P37: HSBC | Q37: Intern | R37: 44566 | S37: 44562 | T37: Milan, Italy | U37: Banking | V37: 43480 | X37: Associate Consultant
A38: André Gardella | B38: André | D38: Gardella | E38: agardelik@gmail.com | I38: https://www.linkedin.com/andre-gardella-67734/ | J38: Treezor | K38: CEO | L38: 33970 | M38: 35064 | N38: Paris | P38: Société Générale | Q38: Head of Operations and Transformation | R38: 43472 | S38: 44927 | T38: Paris | U38: Banking | V38: 34236 | W38: 34824 | X38: International Manager
A39: Andrea Augusto Baroni | B39: Andrea | C39: Augusto | D39: Baroni | E39: andrea.augusto.baroni@gmail.com | I39: https://www.linkedin.com/aabaroni/ | J39: Barclays | K39: VP Data Science | L39: 41548 | M39: 42278 | N39: London, United Kingdom | O39: Banking | P39: Travelport | Q39: Lead Data Scientist | R39: 42741 | S39: 43105 | T39: London, United Kingdom | U39: Technology | V39: 41666 | W39: 42268 | X39: Treasurer
A40: Andrea Bergamini | B40: Andrea | D40: Bergamini | E40: anbergamini@gmail.com | G40: +39 338 5455938 | I40: https://www.linkedin.com/andrea-bergamini-4695b6/ | J40: Electrolux | K40: European Category Director | L40: 38838 | M40: 39722 | N40: Stockholm | O40: Technology | P40: Whirpool | Q40: Strategic Planner Manager | R40: 42008 | S40: 42016 | T40: Comerio | U40: Technology | V40: 38860 | W40: 39882 | X40: Vice President
A41: Andrea Bertè | B41: Andrea | D41: Bertè | I41: https://www.linkedin.com/andrea-berte-38446947/ | J41: Amazon | K41: Head of Product and Market Consumables | L41: 37987 | M41: 40178 | N41: Dubai | O41: Retail | P41: Zeb Consulting | Q41: Manager | R41: 42740 | S41: 43105 | T41: Milan, Italy | U41: Consulting | V41: 39329 | W41: 40190 | X41: Associate Consultant
A42: Andrea Carvelli | B42: Andrea | D42: Carvelli | E42: andrea.carvelli@lw.com | G42: +39 345 8546918 | I42: https://www.linkedin.com/andrea-carvelli/ | J42: Latham & Watkins | K42: Trainee | L42: 43891 | M42: 45291 | N42: Milan, Italy | O42: Private Equity | P42: Baker McKenzie Italia | Q42: Intern | R42: 44201 | S42: 44204 | T42: Milan, Italy | U42: Advisory | X42: Associate Consultant
A43: Andrea Di Benedetto | B43: Andrea | D43: Di Benedetto | I43: https://www.linkedin.com/andrea-di-benedetto-bbb463111/ | J43: Delta Partners | K43: Consultant | L43: 43497 | M43: 44105 | N43: Dubai | P43: Persado | Q43: Intern | R43: 44572 | S43: 44199 | T43: Milan, Italy | V43: 43626 | X43: Associate Consultant
A44: Andrea Di Pietrantonio | B44: Andrea | D44: Di Pietrantonio | E44: andricon@hotmail.it | I44: https://www.linkedin.com/andreadipietrantonio | J44: McKinsey & Company | K44: Engagement Manager | L44: 40544 | M44: 41030 | N44: Helsinki | O44: Consulting | P44: Inventure | Q44: Portfolio Operations Director | R44: 42740 | S44: 44570 | T44: Helsinki | U44: Private Equity | V44: 40568 | W44: 41296 | X44: Vice President
A45: Andrea Gerosa | B45: Andrea | D45: Gerosa | E45: andreagerosa@hotmail.com | I45: https://www.linkedin.com/andreagerosa | J45: ThinkYoung | K45: Founder | L45: 37257 | M45: 38717 | N45: Brussels | O45: Education | P45: International Trademark Association (INTA) | Q45: Member of the Advisory Board | R45: 42736 | T45: New York | U45: Non profit | V45: 37642 | W45: 39083 | X45: Associate Consultant
A46: Andrea Gherzi | B46: Andrea | D46: Gherzi | E46: a.gherzi@hotmail.it | G46: +39 328 927521 | I46: https://www.linkedin.com/andrea-gherzi-21a4416/ | J46: Credit Suisse | K46: Director | L46: 39083 | M46: 40178 | N46: London, United Kingdom | O46: Banking | X46: Associate Consultant
A47: Andrea Ghizzoni | B47: Andrea | D47: Ghizzoni | E47: andrea.ghizzoni79@gmail.com | G47: +39 342 8982383 | I47: https://www.linkedin.com/andreaghizzoni/ | J47: Facile.it | K47: CEO | L47: 36069 | M47: 37591 | N47: Milan, Italy | O47: Technology | P47: Vodafone | Q47: Head of Strategy | R47: 43476 | S47: 44204 | T47: Milan, Italy | U47: Technology | V47: 37013 | W47: 37649 | X47: Associate Consultant
A48: Andrea La Torre | B48: Andrea | D48: La Torre | E48: andrealatorre.alt@gmail.com | G48: +39 325 58453 | I48: https://www.linkedin.com/andrea-la-torre-34b67b7/ | J48: Starting Finance | K48: Author | L48: 43709 | N48: Milan, Italy | O48: Education | V48: 43843 | X48: Associate Consultant
A49: Andrea Lazzari | B49: Andrea | D49: Lazzari | E49: andrea.lazzari@gmail.com | I49: https://www.linkedin.com/andrea-lazzari-94158519 | J49: Venice Investment | K49: Partner | L49: 36526 | M49: 38717 | N49: London, United Kingdom | O49: Investments | P49: Credit Suisse | Q49: Analyst | R49: 44934 | S49: 47125 | U49: Banking | V49: 37387 | W49: 38007 | X49: Associate Consultant
A50: Andrea Lippa | B50: Andrea | D50: Lippa | E50: alippa@bu.edu | I50: https://www.linkedin.com/andrea-lippa-26718311b/ | J50: McKinsey & Company | K50: Business Analyst | L50: 43160 | M50: 43891 | N50: Milan, Italy | O50: Consulting | P50: White Bridge Investments | Q50: Private Equity Analyst Intern | R50: 44197 | S50: 44200 | U50: Private Equity | V50: 43255 | W50: 43631 | X50: Associate Consultant
A51: Andrea Maggi | B51: Andrea | D51: Maggi | E51: an.maggi93@gmail.com | G51: +39 366 449225 | I51: https://www.linkedin.com/in/maggiandrea | J51: Accenture | K51: Digital Marketing Consultant | L51: 42278 | M51: 43009 | N51: Milan, Italy | O51: Consulting | P51: Emirates Investment Bank pjsc | Q51: Intern | R51: 42742 | S51: 42736 | U51: Banking | X51: Vice President
A52: Andrea Maralla | B52: Andrea | D52: Maralla | E52: andrea.maralla@fastwebnet.it | V52: 33419 | W52: 34233 | X52: Associate Consultant
A53: Andrea Matranga | B53: Andrea | D53: Matranga | E53: andreamatranga@gmail.com | G53: +39 334 38322 | I53: https://www.linkedin.com/amatranga | J53: Chapman University | K53: Assistant Professor | L53: 37257 | M53: 38717 | N53: Orange County | O53: Education | P53: New Economic School | Q53: Assistant Professor | R53: 42012 | T53: Moscow | U53: Education | V53: 38475 | W53: 38860 | X53: Associate Consultant
A54: Andrea Paladini | B54: Andrea | D54: Paladini | E54: paladini.andre@gmail.com | I54: https://www.linkedin.com/andrea-paladini-6b884a77 | J54: Amazon | K54: Head of Vendor Management | L54: 40817 | M54: 41791 | N54: Milan, Italy | O54: Retail | P54: Bain & Company | Q54: Consultant | R54: 42013 | S54: 44565 | T54: Milan, Italy | U54: Consulting | V54: 40567 | W54: 41799 | X54: Associate Consultant
A55: Andrea Ronchiato | B55: Andrea | D55: Ronchiato | E55: andrearonchiato@hotmail.com | I55: https://www.linkedin.com/andrea-ronchiato-8216512/ | J55: SC LOWY | K55: Sourcing & Origination | L55: 33604 | M55: 35795 | N55: London, United Kingdom | P55: StormHarbour Securities LLP | Q55: Managing Director | R55: 42370 | S55: 44201 | T55: London, United Kingdom | U55: Financial Services | V55: 34658 | W55: 34974 | X55: Associate Consultant
A56: Andrea Salsi | B56: Andrea | D56: Salsi | E56: andrea.salsi@hotmail.it | G56: +39 392 7531283 | I56: https://www.linkedin.com/andrea-salsi-6722339 | J56: Hogal Lovells | K56: Senior Associate | L56: 38749 | M56: 39356 | N56: London, United Kingdom | O56: Legal | P56: Montecristo RE | Q56: Co-Founder | R56: 44927 | T56: Milan, Italy | V56: 39098 | W56: 39882 | X56: Associate Consultant
A57: Andrea Salvati | B57: Andrea | D57: Salvati | I57: https://www.linkedin.com/andrea-salvati | J57: Cleo | K57: Lead Analytics Engineer | L57: 42278 | M57: 43221 | P57: DAZN | Q57: Lead Analytics Engineer | R57: 43474 | S57: 44927 | T57: London, United Kingdom | U57: Entertainment | V57: 42380 | W57: 43251 | X57: Head of IT
A58: Andrea Schettini | B58: Andrea | D58: Schettini | E58: andrea.schettini22@gmail.com | G58: +39 338 6336965 | I58: https://www.linkedin.com/andreaschettini | J58: Bluegem Capital Partners | K58: Investment Associate | L58: 41913 | M58: 42979 | N58: London, United Kingdom | O58: Private Equity | V58: 42023 | W58: 42982 | X58: Associate Consultant
A59: Andrea Tel | B59: Andrea | D59: Tel | E59: andrea.tel@gmail.com | G59: +44 7447 54 2 7 | I59: https://www.linkedin.com/andreatel | J59: Amazon | K59: Competition and Regulatory Litigation Counsel | L59: 38261 | M59: 40238 | N59: Milan, Italy | O59: Retail | P59: BAT | Q59: Senior Legal Counsel | R59: 42746 | S59: 44201 | T59: London, United Kingdom | V59: 38356 | X59: Associate Consultant
A60: Aneta Kacprzak | B60: Aneta | D60: Kacprzak | V60: 37278 | W60: 38007 | X60: Associate Consultant
A61: Angela Filippa | B61: Angela | D61: Filippa | E61: afilippa1@nyc.rr.com | I61: https://www.linkedin.com/angela-filippa-942369161/ | J61: Credit Suisse | K61: Credit Risk Manager | N61: New York | O61: Banking | V61: 33865 | W61: 34236 | X61: Associate Consultant
A62: Angelo Peluffo | B62: Angelo | D62: Peluffo | I62: https://www.linkedin.com/angelopeluffo/ | J62: FCA | K62: Sales Area Manager | L62: 33482 | M62: 33573 | N62: Bologna | O62: Automotive | P62: BASF COATINGS REFINISH S.p.A | Q62: Business Development Manager | R62: 44199 | S62: 44197 | T62: Milan, Italy | U62: Chemistry | V62: 33419 | W62: 34233 | X62: Associate Consultant
A63: Angelo Solarino | B63: Angelo | D63: Solarino | E63: asolarin@live.com | I63: https://www.linkedin.com/angelo-solarino-94696314/ | J63: Durham University | K63: Associate Professor in Strategy | L63: 39508 | M63: 40452 | N63: Durham | O63: Education | P63: Leeds University Business School | Q63: Lecturer | R63: 42375 | S63: 44205 | T63: Leeds | U63: Education | X63: Associate Consultant
A64: Anjeza Tufina | B64: Anjeza | D64: Tufina | E64: tufina@gmail.com | G64: +39 392 9599186 | V64: 38860 | W64: 39406 | X64: Associate Consultant
A65: Anna Ambrosi | B65: Anna | D65: Ambrosi | E65: anna.ambrosi@gmail.com | G65: +39 349 75946 | I65: https://www.linkedin.com/annaambrosi/ | J65: Anna Ambrosi Interior Design | K65: Freelance | L65: 37712 | M65: 39448 | N65: London, United Kingdom | O65: Art & Design | P65: Bianco Photography | Q65: Owner | R65: 40911 | S65: 44568 | U65: Art & Design | V65: 38007 | W65: 39469 | X65: Associate Consultant
A66: Anna Barzanti | B66: Anna | D66: Barzanti | E66: barzantianna@gmail.com | I66: https://www.linkedin.com/anna-barzanti | J66: Nuove Sales | K66: Sales Associate & Business Development | L66: 40544 | M66: 42370 | N66: Boston | O66: Consulting | P66: Polti North America | Q66: Sales Associate | R66: 44562 | T66: Palo Alto | U66: Consumer Goods | V66: 40567 | W66: 41157 | X66: Associate Consultant
A67: Anna Claudia Schirò | B67: Anna | C67: Claudia | D67: Schirò | V67: 42380 | X67: Associate Consultant
A68: Anna Latini | B68: Anna | D68: Latini | I68: https://www.linkedin.com/anna-latini-bb8b8b128 | J68: CVC Capital Partners | K68: Investment executive | L68: 42005 | M68: 43465 | N68: London, United Kingdom | O68: Investments | P68: Goldman Sachs | Q68: Investment banking analyst | R68: 43471 | S68: 44567 | T68: London, United Kingdom | U68: Banking | V68: 42886 | X68: Associate Consultant
A69: Anna Vittoria Robbi | B69: Anna | C69: Vittoria | D69: Robbi | E69: anna_robbi@yahoo.com | G69: +39 348 366266 | I69: https://www.linkedin.com/annarobbi | J69: Heidrick & Struggles | K69: Manager | N69: London, United Kingdom | O69: Consulting | V69: 41799 | W69: 42534 | X69: Associate Consultant
A70: Annunziato Garofalo | B70: Annunziato | D70: Garofalo | V70: 33240 | W70: 34233 | X70: Associate Consultant
A71: Antonella Marzorati | B71: Antonella | D71: Marzorati | V71: 37013 | W71: 37649 | X71: Associate Consultant
A72: Antonino Musumeci | B72: Antonino | D72: Musumeci | E72: musumeciantonino@gmail.com | G72: +39 349 3143139 | I72: https://www.linkedin.com/antoninom/ | J72: Accenture | K72: Sales Excellence | L72: 38626 | M72: 38991 | N72: Singapore | O72: Consulting | P72: Standard & Poor's | Q72: Research Assistant | R72: 44933 | S72: 47123 | V72: 38732 | W72: 39083 | X72: Associate Consultant
A73: Antonio Attinà | B73: Antonio | D73: Attinà | E73: antonio_attina@hotmail.com | I73: https://www.linkedin.com/antonio-attin%C3%A-pmp-389721/ | J73: BTO Research | K73: Head of Consulting | L73: 37288 | M73: 37500 | N73: Milan, Italy | O73: Education | V73: 37278 | W73: 38007 | X73: Associate Consultant
A74: Antonio Centola | B74: Antonio | D74: Centola | E74: antoniocentola@hotmail.com | I74: https://www.linkedin.com/antonio-centola-a8651aa/ | J74: Accenture | K74: Consulting Lead Director | L74: 36892 | M74: 38717 | N74: Sydney | O74: Consulting | P74: MTN | Q74: General Manager Group Pricing and Value Proposition | R74: 42736 | S74: 44207 | T74: Johannesburg | U74: Legal | V74: 37642 | W74: 38860 | X74: Associate Consultant
A75: Antonio Lai | B75: Antonio | D75: Lai | E75: antonio_lai@yahoo.com | G75: +39 329 115115 | I75: https://www.linkedin.com/antoniolai/ | J75: European Commission | K75: Policy Officer | L75: 38139 | M75: 39783 | N75: Brussels | O75: Public Policy | P75: Qlik | Q75: Legal Counsel | R75: 42375 | S75: 43104 | T75: London, United Kingdom | U75: Legal | V75: 38356 | W75: 39882 | X75: Associate Consultant
A76: Antonio Oteri | B76: Antonio | D76: Oteri | E76: antonio.oteri@gmail.com | G76: +55 119 822 237 12 | I76: https://www.linkedin.com/aoteri/ | J76: Citel Group | K76: Especialista Senior de Qualidade | L76: 32295 | M76: 32843 | N76: Sao Paulo | P76: Forneria Romana | Q76: Owner | R76: 43107 | S76: 44568 | T76: Sao Paulo | V76: 32464 | W76: 33238 | X76: Founder | Y76: Associate Consultant
A77: Antonio Pio Maude | B77: Antonio | C77: Pio | D77: Maude | E77: antonio.maude@icloud.com | L77: 44440 | M77: 44835 | X77: Associate Consultant
A78: Antonio Pisu | B78: Antonio | D78: Pisu | E78: antoniopisu@hotmail.com | G78: +39 328 931338 | I78: https://www.linkedin.com/antonio-pisu-3ab463/ | J78: Mediacomm Srl | K78: Managing Director | L78: 36892 | M78: 38352 | P78: PWC | Q78: Assistant | R78: 44935 | S78: 46027 | V78: 37278 | W78: 38007 | X78: Associate Consultant
A79: Antonio Specchia | B79: Antonio | D79: Specchia | G79: +39 349 48135 | H79: +39 339 752484 | I79: https://www.linkedin.com/antonio-specchia-a34622 | J79: Webuild | K79: HR Country Manager | L79: 37530 | M79: 38322 | N79: Bucarest | P79: Saipem | Q79: HR Business Partner | R79: 44929 | S79: 44569 | T79: Milan, Italy | U79: Energy | V79: 37642 | W79: 38007 | X79: Associate Consultant
A80: Antonio Ventura | B80: Antonio | D80: Ventura | X80: Associate Consultant
A81: Antonio Volpone | B81: Antonio | D81: Volpone | E81: antonio.volpone@gmail.com | G81: +39 329 5429528 | I81: https://www.linkedin.com/antonio-volpone-8bb4b | J81: ATER FONDAZIONE | K81: Administrative Director and Coordinator of the Regional Observatory for Performing Arts | L81: 37622 | M81: 39082 | N81: Modena | O81: Entertainment | P81: Ente Mostra Internazionale del Cinema Libero | Q81: Business Administration Manager | R81: 41280 | S81: 43102 | T81: Bologna | U81: Entertainment | V81: 38356 | X81: Associate Consultant
A82: Arianna Libratti | B82: Arianna | D82: Libratti | E82: arianna.libratti@sinsys.net | I82: https://www.linkedin.com/arianna-libratti-5773396/ | J82: Nexi Group | K82: Head of Commercial Planning - Issuing | O82: Banking | P82: SIA spa | Q82: Head of Bid Management | R82: 41278 | S82: 43101 | T82: Milan, Italy | U82: Technology | V82: 35488 | W82: 37313 | X82: Associate Consultant
A83: Armando Cianci | B83: Armando | D83: Cianci | I83: https://www.linkedin.com/armandocianci | J83: Assist Digital | K83: Product Manager | L83: 41671 | M83: 42186 | N83: Milan, Italy | O83: Technology | P83: Innext | Q83: Consultant | R83: 42736 | S83: 43467 | T83: Milan, Italy | U83: Consulting | V83: 41799 | W83: 42159 | X83: Associate Consultant
A84: Armando Del Vecchio | B84: Armando | D84: Del Vecchio | E84: armando.delvecchioat@gmail.com | G84: +39 346 35168 | V84: 40323 | W84: 41533 | X84: Associate Consultant
A85: Attilio De Luca | B85: Attilio | D85: De Luca | E85: attilio_de@yahoo.it | G85: +39 347 6193283 | I85: https://www.linkedin.com/attilio-de-luca-76a1757 | J85: Università di Catania | K85: Controller per la rendicontazione di progetti Pon | L85: 36892 | M85: 39082 | N85: Catania | O85: Education | P85: EY | Q85: Consultant | R85: 40550 | S85: 41286 | T85: Milan, Italy | U85: Consulting | V85: 38797 | W85: 39083 | X85: Associate Consultant
A86: Aurelio Tempesta | B86: Aurelio | D86: Tempesta | I86: https://www.linkedin.com/aureliotempesta/details/experience/ | J86: Hiop | K86: Innovation Associate | L86: 43831 | N86: Milan, Italy | V86: 43843 | X86: President | Y86: Secretary General | Z86: Head of IT
A87: Aurora Trentini | B87: Aurora | D87: Trentini | E87: aurora.trentini@gmail.com | I87: https://www.linkedin.com/aurora-trentini-448727157/ | J87: Blackstone | K87: Private Equity Analyst | L87: 42979 | M87: 43983 | N87: London, United Kingdom | O87: Private Equity | P87: J.P. Morgan | Q87: Investment Banking Intern | R87: 44202 | S87: 44204 | T87: London, United Kingdom | U87: Investment Banking | V87: 43115 | W87: 43830 | X87: Associate Consultant
A88: Azzurra Giorgio | B88: Azzurra | D88: Giorgio | E88: azzurra.giorgio@gmail.com | G88: +39 349 467789 | I88: https://www.linkedin.com/azzurragiorgio | J88: Intervieweb | K88: Co-founder | L88: 37895 | M88: 39448 | N88: Torino | O88: Technology | P88: Exton Consulting | Q88: Senior Manager | R88: 41641 | S88: 44567 | T88: Milan, Italy | U88: Consulting | V88: 37797 | W88: 39447 | X88: Associate Consultant
A89: Barbara Cominelli | B89: Barbara | D89: Cominelli | E89: barbara.cominelli@gmail.com | I89: https://www.linkedin.com/in/barbaracominelli/ | J89: JLL | K89: CEO Italy | N89: Milan, Italy | P89: Microsoft | Q89: COO and Deputy CEO | R89: 43103 | S89: 44573 | T89: Milan, Italy | U89: Technology | V89: 33240 | W89: 34236 | X89: Associate Consultant
A90: Barbara Garavaglia | B90: Barbara | D90: Garavaglia | V90: 34236 | W90: 34347 | X90: Associate Consultant
A91: Barbara Mento | B91: Barbara | D91: Mento | E91: barbara.mento@gmail.com | G91: +39 328 6243954 | I91: https://www.linkedin.com/in/barbara-mento-19b9aa6/ | J91: Family District | K91: CEO | L91: 38718 | M91: 39813 | N91: Milan, Italy | P91: Barclays | Q91: Director | R91: 42738 | S91: 44572 | T91: Milan, Italy | U91: Investment Banking | V91: 38860 | W91: 39406 | X91: Associate Consultant
A92: Beatrice Costa | B92: Beatrice | D92: Costa | E92: beatricecosta22@gmail.com | G92: +39 339 1458728 | I92: https://www.linkedin.com/in/beatrice-costa-949926a2/ | J92: Bain & Company | K92: Associate Consultant | L92: 42767 | M92: 43191 | N92: London, United Kingdom | O92: Consulting | P92: B2B Food Group | Q92: CEO Analyst | R92: 43466 | S92: 43477 | T92: Berlin | V92: 33419 | W92: 34233 | X92: Associate Consultant
A93: Beatrice Graziani | B93: Beatrice | D93: Graziani | E93: beatrigraziani@gmail.com | I93: https://www.linkedin.com/in/beatricegraziani/ | J93: McKinsey & Company | K93: Business Analyst | L93: 42856 | M93: 43739 | N93: Milan, Italy | O93: Consulting | P93: Deloitte | Q93: Customer Success Consultant | R93: 44562 | S93: 44566 | T93: Milan, Italy | U93: Consulting | V93: 42886 | W93: 43831 | X93: Head of HR | Y93: International Manager | Z93: Secretary General
A94: Benedetta Ballantini | B94: Benedetta | D94: Ballantini | V94: 34431 | W94: 34633 | X94: Associate Consultant
A95: Berkin Akar | B95: Berkin | D95: Akar | I95: https://www.linkedin.com/in/berkin-akar/ | J95: Columbia Business School | K95: Teaching Assistant | L95: 43983 | M95: 44531 | N95: New York | O95: Education | P95: CITI | Q95: TTS Cash Management | R95: 44201 | S95: 44197 | T95: Instanbul | U95: Banking | X95: Associate Consultant
A96: Biagio Stasi | B96: Biagio | D96: Stasi | E96: biagio.stasi@gmail.com | G96: +39 348 58519 | H96: +39 335 1311833 | I96: https://www.linkedin.com/in/biagiostasi/ | J96: Il Sole 24 Ore | K96: Direttore Commerciale Digital | N96: Milan, Italy | O96: Media & Marketing | P96: Hearst Magazines | Q96: Chief Digital Officer | R96: 40555 | S96: 43106 | T96: Milan, Italy | U96: Media & Marketing | V96: 35104 | W96: 35394 | X96: Associate Consultant
A97: Brian Commaroto Roverini | B97: Brian | D97: Commaroto Roverini | E97: briancommaroto@gmail.com | G97: +39 329 11825 | I97: https://www.linkedin.com/in/brian-commaroto-roverini-6a675b6/ | J97: U.S. Department of State | K97: Foreign Service Officer | L97: 38353 | M97: 39447 | O97: Public Policy | P97: JetBlue | Q97: Senior Financial Analyst and Revenue Management Analyst | R97: 44935 | S97: 44199 | T97: New York | X97: Associate Consultant
A98: Federica Fede Brugnera | B98: Federica | D98: Fede Brugnera | E98: federica_brugnera@yahoo.it | G98: +39 349 3326 | J98: Pisces Inc. | K98: Director of Portfolio Finance | O98: Financial Services | P98: Thin Film Electronics | Q98: Vice-President | R98: 43111 | S98: 43477 | U98: Energy | X98: Associate Consultant
A99: Bruno Cartocci | B99: Bruno | D99: Cartocci | I99: https://www.linkedin.com/in/bruno-cartocci-2391251/ | J99: Equita | K99: Equities Sales Manager | L99: 32874 | M99: 35430 | N99: Milan, Italy | O99: Investments | P99: Banca Akros | Q99: Sales Trader | R99: 1/1/1097 | T99: Milan, Italy | U99: Banking | V99: 33240 | W99: 34233 | X99: Associate Consultant
A100: Maria Giulia Bufano | B100: Maria Giulia | D100: Bufano | E100: maria.giulia.bufano@gmail.com | I100: https://www.linkedin.com/in/maria-giulia-bufano-24a339119 | J100: Embassy of Italy in Kuala Lumpur | K100: Intern | N100: Lumpur | O100: Public Policy | V100: 42513 | W100: 42894 | X100: Associate Consultant
...

Sheet Mesi
B2: gen | C2: 1
B3: feb | C3: 2
B4: mar | C4: 3
B5: apr | C5: 4
B6: mag | C6: 5
B7: giu | C7: 6
B8: lug | C8: 7
B9: ago | C9: 8
B10: set | C10: 9
B11: ott | C11: 10
B12: nov | C12: 11
B13: dic | C13: 12
... B26: Dec | C26: 12

Sheet Industries
A1: Agriculture | B1: =SUM(COUNTIF(#REF!,A1),COUNTIF(#REF!,A1)) -> #REF! | D1: Accounting | E1: 6 | G1: =IF(O2=OR("AI","Business Intelligence", "Computer Software", "Cyber Security", "Information", "Internet", "IT", "IT & Communication", "Tech", "TLC"), "Technology", IF(O2=OR("Construction","Shipbuilding","Maritime"), "Construction", IF(O2 = OR("Public Administration", "Institution", "Public Policy"), "Public Policy", IF( O2 = OR("Management", "Consulting Advisory", "Management Consulting"), "Consulting", IF( O2 = OR("Publishing", "Marketing & Advertising", "Media"), "Media & Marketing", IF( O2 = OR("Electrical/Electronic Manufacturing", "Oil & Energy"), "Energy", IF( O2 = OR("Real Estate", "Fondo (inclusi PE)"), "Investments", IF( O2 = OR("Research", "University"), "Education", O2)))))))) -> #VALUE!
A2: AI | B2: =SUM(COUNTIF(#REF!,A2),COUNTIF(#REF!,A2)) -> #REF! | C2: 1 | D2: Advisory | E2: 6
A3: Business Intelligence | B3: =SUM(COUNTIF(#REF!,A3),COUNTIF(#REF!,A3)) -> #REF! | C3: 1
A4: Construction | B4: =SUM(COUNTIF(#REF!,A4),COUNTIF(#REF!,A4)) -> #REF! | C4: 1 | D4: Automotive | E4: 9
A5: Cyber Security | B5: =SUM(COUNTIF(#REF!,A5),COUNTIF(#REF!,A5)) -> #REF! | C5: 1 | D5: Banking | E5: 87
A6: IT | B6: =SUM(COUNTIF(#REF!,A6),COUNTIF(#REF!,A6)) -> #REF! | C6: 1
A7: Management | B7: =SUM(COUNTIF(#REF!,A7),COUNTIF(#REF!,A7)) -> #REF! | C7: 1 | D7: Consumer goods | E7: 14
A8: Public Administration | B8: =SUM(COUNTIF(#REF!,A8),COUNTIF(#REF!,A8)) -> #REF! | C8: 1 | D8: Corporate Finance | E8: 38
A9: Publishing | B9: =SUM(COUNTIF(#REF!,A9),COUNTIF(#REF!,A9)) -> #REF! | C9: 1
A10: Shipbuilding | B10: =SUM(COUNTIF(#REF!,A10),COUNTIF(#REF!,A10)) -> #REF! | C10: 1 | D10: Defense | E10: 2
A11: Consulting Advisory | B11: =SUM(COUNTIF(#REF!,A11),COUNTIF(#REF!,A11)) -> #REF! | C11: 1 | D11: Education | E11: 35
A12: Energy | B12: =SUM(COUNTIF(#REF!,A12),COUNTIF(#REF!,A12)) -> #REF! | C12: 1 | D12: Engineering | E12: 1
A13: Information | B13: =SUM(COUNTIF(#REF!,A13),COUNTIF(#REF!,A13)) -> #REF! | C13: 1 | D13: Entertainment | E13: 8
A14: Marketing & Advertising | B14: =SUM(COUNTIF(#REF!,A14),COUNTIF(#REF!,A14)) -> #REF! | C14: 1 | D14: Fashion | E14: 4
A15: University | B15: =SUM(COUNTIF(#REF!,A15),COUNTIF(#REF!,A15)) -> #REF! | C15: 1 | D15: Food & Beverage | E15: 15
A16: Maritime | B16: =SUM(COUNTIF(#REF!,A16),COUNTIF(#REF!,A16)) -> #REF! | C16: 1
A17: Electrical/Electronic Manufacturing | B17: =SUM(COUNTIF(#REF!,A17),COUNTIF(#REF!,A17)) -> #REF! | C17: 1
A18: Institution | B18: =SUM(COUNTIF(#REF!,A18),COUNTIF(#REF!,A18)) -> #REF! | C18: 1
A19: Real Estate | B19: =SUM(COUNTIF(#REF!,A19),COUNTIF(#REF!,A19)) -> #REF! | C19: 1
A20: Research | B20: =SUM(COUNTIF(#REF!,A20),COUNTIF(#REF!,A20)) -> #REF! | C20: 1
A21: Media | B21: =SUM(COUNTIF(#REF!,A21),COUNTIF(#REF!,A21)) -> #REF! | C21: 1 | D21: Logistics & Supply Chain | E21: 5
A22: Fondo (inclusi PE) | B22: =SUM(COUNTIF(#REF!,A22),COUNTIF(#REF!,A22)) -> #REF! | C22: 1
A23: TLC | B23: =SUM(COUNTIF(#REF!,A23),COUNTIF(#REF!,A23)) -> #REF! | C23: 1
A24: Computer Software | B24: =SUM(COUNTIF(#REF!,A24),COUNTIF(#REF!,A24)) -> #REF! | C24: 1
A25: Oil & Energy | B25: =SUM(COUNTIF(#REF!,A25),COUNTIF(#REF!,A25)) -> #REF! | C25: 1 | D25: Non profit | E25: 4
A26: Tech | B26: =SUM(COUNTIF(#REF!,A26),COUNTIF(#REF!,A26)) -> #REF! | C26: 1
A27: Technology | B27: =SUM(COUNTIF(#REF!,A27),COUNTIF(#REF!,A27)) -> #REF! | C27: 1 | D27: Private Equity | E27: 24
A28: Internet | B28: =SUM(COUNTIF(#REF!,A28),COUNTIF(#REF!,A28)) -> #REF! | C28: 1
A29: Public Policy | B29: =SUM(COUNTIF(#REF!,A29),COUNTIF(#REF!,A29)) -> #REF! | C29: 1 | D29: Public Policy | E29: 17
A30: IT & Communication | B30: =SUM(COUNTIF(#REF!,A30),COUNTIF(#REF!,A30)) -> #REF! | C30: 1
A31: Investments | B31: =SUM(COUNTIF(#REF!,A31),COUNTIF(#REF!,A31)) -> #REF! | C31: 1
A32: Management Consulting | B32: =SUM(COUNTIF(#REF!,A32),COUNTIF(#REF!,A32)) -> #REF! | C32: 1 | D32: Sustainabilty | E32: 2
A33: Education | B33: =SUM(COUNTIF(#REF!,A33),COUNTIF(#REF!,A33)) -> #REF! | C33: 1
A34: Consulting | B34: =SUM(COUNTIF(#REF!,A34),COUNTIF(#REF!,A34)) -> #REF! | C34: 1
A35: Altro | B35: =SUM(COUNTIF(#REF!,A35),COUNTIF(#REF!,A35)) -> #REF! | C35: 1 | D35: Agriculture | E35: 1
A36: Art | B36: =SUM(COUNTIF(#REF!,A36),COUNTIF(#REF!,A36)) -> #REF! | C36: 1
A37: Business Development | B37: =SUM(COUNTIF(#REF!,A37),COUNTIF(#REF!,A37)) -> #REF! | C37: 1
A38: E-commerce | B38: =SUM(COUNTIF(#REF!,A38),COUNTIF(#REF!,A38)) -> #REF! | C38: 1 | D38: Beauty & Cosmetics | E38: 4
A39: Engineering | B39: =SUM(COUNTIF(#REF!,A39),COUNTIF(#REF!,A39)) -> #REF!
A40: Event management | B40: =SUM(COUNTIF(#REF!,A40),COUNTIF(#REF!,A40)) -> #REF! | C40: 1
A41: Food and Beverage | B41: =SUM(COUNTIF(#REF!,A41),COUNTIF(#REF!,A41)) -> #REF! | C41: 1 | D41: Chemistry | E41: 8
A42: Furniture | B42: =SUM(COUNTIF(#REF!,A42),COUNTIF(#REF!,A42)) -> #REF! | C42: 1
A43: Health | B43: =SUM(COUNTIF(#REF!,A43),COUNTIF(#REF!,A43)) -> #REF! | C43: 1 | D43: Construction | E43: 5
A44: Hospitality | B44: =SUM(COUNTIF(#REF!,A44),COUNTIF(#REF!,A44)) -> #REF! | C44: 1 | D44: Consulting | E44: 140
A45: Operations | B45: =SUM(COUNTIF(#REF!,A45),COUNTIF(#REF!,A45)) -> #REF!
A46: Sport | B46: =SUM(COUNTIF(#REF!,A46),COUNTIF(#REF!,A46)) -> #REF! | D46: Art & Design | E46: 6
A47: Pharmaceutical | B47: 1 | C47: 1
A48: Corporate Finance | B48: =SUM(COUNTIF(#REF!,A48),COUNTIF(#REF!,A48)) -> #REF! | C48: 1
A49: Defense | B49: =SUM(COUNTIF(#REF!,A49),COUNTIF(#REF!,A49)) -> #REF! | D49: Energy | E49: 13
A50: Logistics & Supply Chain | B50: =SUM(COUNTIF(#REF!,A50),COUNTIF(#REF!,A50)) -> #REF! | C50: 1
A51: Pharmaceuticals | B51: =SUM(COUNTIF(#REF!,A51),COUNTIF(#REF!,A51)) -> #REF! | C51: 1 | D51: Financial Services | E51: 14
A52: Sustainabilty | B52: =SUM(COUNTIF(#REF!,A52),COUNTIF(#REF!,A52)) -> #REF!
A53: Human Resources | B53: =SUM(COUNTIF(#REF!,A53),COUNTIF(#REF!,A53)) -> #REF!
A54: Leisure, Travel and Tourism | B54: =SUM(COUNTIF(#REF!,A54),COUNTIF(#REF!,A54)) -> #REF! | C54: 1
A55: Packaging | B55: =SUM(COUNTIF(#REF!,A55),COUNTIF(#REF!,A55)) -> #REF! | C55: 1
A56: Transports | B56: =SUM(COUNTIF(#REF!,A56),COUNTIF(#REF!,A56)) -> #REF! | D56: Hubs | E56: 4
A57: Beauty & Cosmetics | B57: =SUM(COUNTIF(#REF!,A57),COUNTIF(#REF!,A57)) -> #REF! | D57: Human Resources | E57: 3
A58: Fashion | B58: =SUM(COUNTIF(#REF!,A58),COUNTIF(#REF!,A58)) -> #REF!
A59: Hubs | B59: =SUM(COUNTIF(#REF!,A59),COUNTIF(#REF!,A59)) -> #REF! | D59: Insurance | E59: 9
A60: Medical/Healthcare | B60: =SUM(COUNTIF(#REF!,A60),COUNTIF(#REF!,A60)) -> #REF! | C60: 1 | D60: Investment Banking | E60: 25
A61: Non profit | B61: =SUM(COUNTIF(#REF!,A61),COUNTIF(#REF!,A61)) -> #REF! | D61: Investments | E61: 30
A62: Startup | B62: =SUM(COUNTIF(#REF!,A62),COUNTIF(#REF!,A62)) -> #REF! | D62: Legal | E62: 23
A63: Design | B63: =SUM(COUNTIF(#REF!,A63),COUNTIF(#REF!,A63)) -> #REF! | C63: 1 | D63: Leisure, Travel and Tourism | E63: 4
A64: Accounting | B64: =SUM(COUNTIF(#REF!,A64),COUNTIF(#REF!,A64)) -> #REF! | D64: Luxury | E64: 9
A65: Advisory | B65: =SUM(COUNTIF(#REF!,A65),COUNTIF(#REF!,A65)) -> #REF!
A66: Entertainment | B66: =SUM(COUNTIF(#REF!,A66),COUNTIF(#REF!,A66)) -> #REF! | C66: 1 | D66: Media & Marketing | E66: 8
A67: Chemistry | B67: =SUM(COUNTIF(#REF!,A67),COUNTIF(#REF!,A67)) -> #REF! | D67: Medical/Healthcare | E67: 5
A68: Automotive | B68: =SUM(COUNTIF(#REF!,A68),COUNTIF(#REF!,A68)) -> #REF!
A69: Insurance | B69: =SUM(COUNTIF(#REF!,A69),COUNTIF(#REF!,A69)) -> #REF! | D69: Operations | E69: 1
A70: Luxury | B70: =SUM(COUNTIF(#REF!,A70),COUNTIF(#REF!,A70)) -> #REF! | D70: Other | E70: 11
A71: Other | B71: =SUM(COUNTIF(#REF!,A71),COUNTIF(#REF!,A71)) -> #REF! | C71: 1 | D71: Pharmaceuticals | E71: 3
A72: Consumer goods | B72: =SUM(COUNTIF(#REF!,A72),COUNTIF(#REF!,A72)) -> #REF! | C72: 1
A73: Financial Services | B73: =SUM(COUNTIF(#REF!,A73),COUNTIF(#REF!,A73)) -> #REF! | C73: 1
A74: Food & Beverage | B74: =SUM(COUNTIF(#REF!,A74),COUNTIF(#REF!,A74)) -> #REF! | C74: 1 | D74: Retail | E74: 24
A75: Legal | B75: =SUM(COUNTIF(#REF!,A75),COUNTIF(#REF!,A75)) -> #REF! | D75: Sport | E75: 1
A76: Retail | B76: =SUM(COUNTIF(#REF!,A76),COUNTIF(#REF!,A76)) -> #REF! | C76: 1 | D76: Startup | E76: 4
A77: Private Equity | B77: =SUM(COUNTIF(#REF!,A77),COUNTIF(#REF!,A77)) -> #REF!
A78: Investment Banking | B78: =SUM(COUNTIF(#REF!,A78),COUNTIF(#REF!,A78)) -> #REF! | D78: Technology | E78: 62
A79: Corporate | B79: =SUM(COUNTIF(#REF!,A79),COUNTIF(#REF!,A79)) -> #REF! | C79: 1 | D79: Transports | E79: 3
A80: Banking | B80: =SUM(COUNTIF(#REF!,A80),COUNTIF(#REF!,A80)) -> #REF!
